Workbook

Sheet Footloose Financial Statements
A1: All figures are in $thousands
B2: 2013 Actual | C2: 2014 Actual | D2: 2015 Actual | E2: 2016 Actual | F2: 2017 Actual | G2: 2018 Actual | H2: 2019 Actual | I2: 2020 Actual | J2: 2021 Actual | K2: 2022 Actual | L2: 2023 Forecast | N2: EXTERNAL FUNDING REQUIRED | O2: =L29-L37-L38 -> 30288.325
A3: PROFIT AND LOSS STATEMENT
A4: Operating revenue | B4: 78380 | C4: 109256 | D4: 196439 | E4: 259738 | F4: 323190 | G4: 369086 | H4: 446739 | I4: 314395 | J4: 173492 | K4: 375327 | L4: =V5 -> 394093.35 | N4: Assumptions | P4: Comments | R4: Task | S4: Variables | T4: Variable | U4: Calculation | V4: Original Value
A5: Other revenue | B5: 383 | C5: 966 | D5: 1383 | E5: 4946 | F5: 2487 | G5: 3019 | H5: 2744 | I5: 35510 | J5: 26960 | K5: 13355 | L5: =L4*O6 -> 14022.75 | N5: Operating revenue forecast for 2025 | O5: =K4*1.05 -> 394093.35 | P5: The operating revenue is expected to be a modest 5% higher in 2023; | R5: 3 | S5: Q.1 | T5: Operating Revenue | U5: 382616.77 | V5: =O5 -> 394093.35
A6: Total revenue | B6: =B4+B5 -> 78763 | C6: =C4+C5 -> 110222 | D6: =D4+D5 -> 197822 | E6: =E4+E5 -> 264684 | F6: =F4+F5 -> 325677 | G6: =G4+G5 -> 372105 | H6: =H4+H5 -> 449483 | I6: =I4+I5 -> 349905 | ... L6: =L4+L5 -> 408116.1 | N6: Other revenue/operating revenue | O6: =K5/$K$4 -> 0.035582306 | P6: Same percentage of operating revenue as they were in FY2022 | T6: Change in Operating Revenue | U6: =U5-K4 -> 7289.77 | V6: 0
A7: Operating expenses | B7: -57765 | C7: -81360 | D7: -148727 | E7: -195654 | F7: -227062 | G7: -246655 | H7: -299101 | I7: -214683 | J7: -207619 | K7: -328775 | L7: =V9 -> -297046.68 | N7: Operating expenses/operating revenue | O7: =-(100000+0.5*L4) -> -297046.68 | P7: Assumes to be calculated using the formula Operating expense = $100 million + 0.5 × Operating revenue | S7: Q.2 | T7: Operating Revenue | U7: =H4 -> 446739 | V7: =U5 -> 382616.77
A8: Depreciation and amortisation | B8: -2079 | C8: -3599 | D8: -7540 | E8: -10562 | F8: -16157 | G8: -17833 | H8: -20348 | I8: -42512 | J8: -40857 | K8: -44423 | L8: =O8*L4 -> -46644.15 | N8: Depreciation and amortization | O8: =K8/K4 -> -0.11835813 | P8: Same percentage of operating revenue as they were in FY2022 | T8: =A21 -> Accounts receivables | U8: =H21 -> 328771 | V8: =(K21/$K$4)*$L$4 -> 295115.1
A9: Total expenses | B9: =B7+B8 -> -59844 | C9: =C7+C8 -> -84959 | D9: =D7+D8 -> -156267 | E9: =E7+E8 -> -206216 | F9: =F7+F8 -> -243219 | G9: =G7+G8 -> -264488 | H9: =H7+H8 -> -319449 | I9: =I7+I8 -> -257195 | ... L9: =L7+L8 -> -343690.83 | N9: Interest expense | O9: =K11 -> -2303 | P9: Assumed to stay the same value as in 2022 | S9: Q.3 | T9: Operating Expenses | U9: =-(75000+0.6*L4) -> -311456.01 | V9: =O7 -> -297046.68
A10: Profit before interest and tax (EBIT) | B10: =B6+B9 -> 18919 | C10: =C6+C9 -> 25263 | D10: =D6+D9 -> 41555 | E10: =E6+E9 -> 58468 | F10: =F6+F9 -> 82458 | G10: =G6+G9 -> 107617 | H10: =H6+H9 -> 130034 | I10: =I6+I9 -> 92710 | ... L10: =L6+L9 -> 64425.275 | N10: Tax rate | O10: 0.3 | P10: Assumed to be 30% if NPBT is Positive | R10: 4 | S10: Q.1 | T10: Interest Expense | U10: =-3634.56+V10 -> -5937.56 | V10: =K11 -> -2303
A11: Interest expense | B11: -724 | C11: -640 | D11: -959 | E11: -1809 | F11: -3443 | G11: -3226 | H11: -2765 | I11: -9620 | J11: -3267 | K11: -2303 | L11: =V10 -> -2303 | N11: Total current assets/operating revenue | O11: =K24/K4 -> 1.1764968 | P11: Same percentage of operating revenue as they were in FY2022
A12: Profit before tax | B12: =B10+B11 -> 18195 | C12: =C10+C11 -> 24623 | D12: =D10+D11 -> 40596 | E12: =E10+E11 -> 56659 | F12: =F10+F11 -> 79015 | G12: =G10+G11 -> 104391 | H12: =H10+H11 -> 127269 | I12: =I10+I11 -> 83090 | ... L12: =L10+L11 -> 62122.275 | N12: Total non-current assets/operating revenue | O12: =K36/K4 -> 0.1236202 | P12: Same percentage of operating revenue as they were in FY2022
A13: Tax Expense | B13: -6702 | C13: -6799 | D13: -10162 | E13: -12126 | F13: -19788 | G13: -23232 | H13: -32743 | I13: -18171 | J13: 19018 | K13: -771 | L13: =IF(L12>0,-1*30%*L12,0) -> -18636.682 | N13: Accounts payable/operating revenue | O13: =K30/K4 -> 0.90978533 | P13: Same percentage of operating revenue as they were in FY2022
A14: Net profit (or loss) | B14: =B12+B13 -> 11493 | C14: =C12+C13 -> 17824 | D14: =D12+D13 -> 30434 | E14: =E12+E13 -> 44533 | F14: =F12+F13 -> 59227 | G14: =G12+G13 -> 81159 | H14: =H12+H13 -> 94526 | I14: =I12+I13 -> 64919 | ... L14: =L12+L13 -> 43485.592 | N14: Other current liabilities/operating revenue | O14: =K23/K4 -> 0.04538176 | P14: Same percentage of operating revenue as they were in FY2022
N15: Other non-current liabilities/operating revenue | O15: =K35/K4 -> 0.023438229 | P15: Same percentage of operating revenue as they were in FY2022
A16: Dividends paid | B16: -7497 | C16: -9129 | D16: -13523 | E16: -20983 | F16: -30514 | G16: -37471 | H16: -45271 | I16: -26456 | J16: 0 | K16: 0 | L16: =-5%*L4 -> -19704.668 | N16: Short-term debt | O16: =L31 -> 11288.55 | P16: Same percentage of operating revenue as they were in FY2022
N17: Long-term debt | O17: =L34 -> 39481.05 | P17: Same percentage of operating revenue as they were in FY2022
B18: 2013 Actual | C18: 2014 Actual | D18: 2015 Actual | E18: 2016 Actual | F18: 2017 Actual | G18: 2018 Actual | H18: 2019 Actual | I18: 2020 Actual | J18: 2021 Actual | K18: 2022 Actual | L18: 2023 Forecast | N18: Dividend payout ratio (dividends/net profit) | O18: =ABS(L16/L14) -> 0.45313094 | P18: Dividend assumed to be 5% of Operating Revenue
A19: BALANCE SHEET
A20: Cash | B20: 13535 | C20: 32000 | D20: 40663 | E20: 81178 | F20: 79217 | G20: 84297 | H20: 138791 | I20: 92843 | J20: 99018 | K20: 142054 | L20: =(K20/$K$4)*$L$4 -> 149156.7 | N20: Analysis
A21: Accounts receivables | B21: 27975 | C21: 101286 | D21: 153398 | E21: 168130 | F21: 201210 | G21: 252237 | H21: 328771 | I21: 64535 | J21: 175428 | K21: 281062 | L21: =V8 -> 295115.1 | N21: EBIT= | O21: =ABS(L9) -> 343690.83
A22: Inventories | B22: 0 | C22: 0 | D22: 0 | E22: 0 | F22: 0 | G22: 0 | H22: 0 | I22: 0 | J22: 884 | K22: 1422 | L22: =(K22/$K$4)*$L$4 -> 1493.1 | N22: Funding Required= | O22: =ABS(O2) -> 30288.325
A23: Other current assets | B23: 706 | C23: 1979 | D23: 4643 | E23: 4918 | F23: 4462 | G23: 4203 | H23: 10576 | I23: 16444 | J23: 15344 | K23: 17033 | L23: =(K23/$K$4)*$L$4 -> 17884.65 | N23: Tax Rate= | O23: 0.3
A24: Total current assets | B24: =B20+B21+B22+B23 -> 42216 | C24: =C20+C21+C22+C23 -> 135265 | D24: =D20+D21+D22+D23 -> 198704 | E24: =E20+E21+E22+E23 -> 254226 | F24: =F20+F21+F22+F23 -> 284889 | G24: =G20+G21+G22+G23 -> 340737 | H24: =H20+H21+H22+H23 -> 478138 | I24: =I20+I21+I22+I23 -> 173822 | ... L24: =L20+L21+L22+L23 -> 463649.55 | N24: Interest Rate on Debt= | O24: 0.12
A25: Fixed assets | B25: 3166 | C25: 3371 | D25: 3697 | E25: 5426 | F25: 5262 | G25: 6118 | H25: 13328 | I25: 58919 | J25: 51681 | K25: 54014 | L25: =(K25/$K$4)*$L$4 -> 56714.7 | N25: Debt without additional financing= | O25: =L37 -> 447070.05
A26: Goodwill | B26: 72876 | C26: 94260 | D26: 215555 | E26: 280107 | F26: 393238 | G26: 407187 | H26: 453522 | I26: 478211 | J26: 0 | K26: 859193 | L26: =(K26/$K$4)*$L$4 -> 902152.65 | N26: Equity without additional financing= | O26: =L38 -> 1105165.9
A27: Other non-current assets | B27: 2838 | C27: 14869 | D27: 22452 | E27: 30388 | F27: 56766 | G27: 50799 | H27: 58861 | I27: 52565 | J27: 793393 | K27: 152388 | L27: =(K27/$K$4)*$L$4 -> 160007.4
A28: Total non-current assets | B28: =B25+B26+B27 -> 78880 | C28: =C25+C26+C27 -> 112500 | D28: =D25+D26+D27 -> 241704 | E28: =E25+E26+E27 -> 315921 | F28: =F25+F26+F27 -> 455266 | G28: =G25+G26+G27 -> 464104 | H28: =H25+H26+H27 -> 525711 | I28: =I25+I26+I27 -> 589695 | ... L28: =L25+L26+L27 -> 1118874.8 | N28: Only Equity-Based Financing Option
A29: Total assets | B29: =B24+B28 -> 121096 | C29: =C24+C28 -> 247765 | D29: =D24+D28 -> 440408 | E29: =E24+E28 -> 570147 | F29: =F24+F28 -> 740155 | G29: =G24+G28 -> 804841 | H29: =H24+H28 -> 1003849 | I29: =I24+I28 -> 763517 | ... L29: =L24+L28 -> 1582524.3 | N29: ROIC | O29: =(O21*(1-O23))/(O25+O26+O22) -> 0.1520252
A30: Account payable | B30: 26048 | C30: 94126 | D30: 148385 | E30: 202720 | F30: 233049 | G30: 253621 | H30: 316753 | I30: 100499 | J30: 204745 | K30: 341467 | L30: =(K30/$K$4)*$L$4 -> 358540.35 | N30: ROE | O30: =O33+(O33-O24*(1-O23))*(O25/(O26+O22)) -> 0.17880922
A31: Short-term debt | B31: 3192 | C31: 0 | D31: 0 | E31: 14347 | F31: 18122 | G31: 14677 | H31: 19205 | I31: 8672 | J31: 9193 | K31: 10751 | L31: =(K31/K4)*L4 -> 11288.55
A32: Other current liabilities | B32: 2421 | C32: 10910 | D32: 17004 | E32: 20226 | F32: 22750 | G32: 23096 | H32: 31876 | I32: 33826 | J32: 18155 | K32: 27165 | L32: =(K32/$K$4)*$L$4 -> 28523.25 | N32: Only Debt-Based Financing Option
A33: Total current liabilities | B33: =B30+B31+B32 -> 31661 | C33: =C30+C31+C32 -> 105036 | D33: =D30+D31+D32 -> 165389 | E33: =E30+E31+E32 -> 237293 | F33: =F30+F31+F32 -> 273921 | G33: =G30+G31+G32 -> 291394 | H33: =H30+H31+H32 -> 367834 | I33: =I30+I31+I32 -> 142997 | ... L33: =L30+L31+L32 -> 398352.15 | N33: ROIC | O33: =(O21*(1-O23))/(O25+O26+O22) -> 0.1520252
A34: Long-term debt | B34: 157 | C34: 0 | D34: 0 | E34: 22833 | F34: 27301 | G34: 29301 | H34: 20085 | I34: 44423 | J34: 37188 | K34: 37601 | L34: =(K34/K4)*L4 -> 39481.05 | N34: ROE | O34: =O33+(O33-O24*(1-O23))*((O25+O22)/O26) -> 0.18140758
A35: Other non-current liabilities | B35: 16293 | C35: 9845 | D35: 39108 | E35: 38436 | F35: 37529 | G35: 12654 | H35: 23448 | I35: 18010 | J35: 15010 | K35: 8797 | L35: =(K35/$K$4)*$L$4 -> 9236.85
A36: Total non-current liabilities | B36: =B34+B35 -> 16450 | C36: =C34+C35 -> 9845 | D36: =D34+D35 -> 39108 | E36: =E34+E35 -> 61269 | F36: =F34+F35 -> 64830 | G36: =G34+G35 -> 41955 | H36: =H34+H35 -> 43533 | I36: =I34+I35 -> 62433 | ... L36: =L34+L35 -> 48717.9
A37: Total liabilities | B37: =B36+B33 -> 48111 | C37: =C36+C33 -> 114881 | D37: =D36+D33 -> 204497 | E37: =E36+E33 -> 298562 | F37: =F36+F33 -> 338751 | G37: =G36+G33 -> 333349 | H37: =H36+H33 -> 411367 | I37: =I36+I33 -> 205430 | ... L37: =L36+L33 -> 447070.05
A38: Owners' equity | B38: =B29-B37 -> 72985 | C38: =C29-C37 -> 132884 | D38: =D29-D37 -> 235911 | E38: =E29-E37 -> 271585 | F38: =F29-F37 -> 401404 | G38: =G29-G37 -> 471492 | H38: =H29-H37 -> 592482 | I38: =I29-I37 -> 558087 | ... K38: =K29-K37 -> 1081385 | L38: =K38+(1-O18)*L14 -> 1105165.9
A40: Market capitalisation | B40: 299390 | C40: 553490 | D40: 966700 | E40: 1327380 | F40: 2345220 | G40: 2814490 | H40: 2371740 | I40: 1026220 | J40: 2931780 | K40: 2688930

Sheet Footloose Ratio Analysis
A1: All figures are in $thousands | N1: Horizontal Analysis | P1: Vertical Analysis
B2: 2013 Actual | C2: 2014 Actual | D2: 2015 Actual | E2: 2016 Actual | F2: 2017 Actual | G2: 2018 Actual | H2: 2019 Actual | I2: 2020 Actual | J2: 2021 Actual | K2: 2022 Actual | L2: Percentage Calculation | M2: 2023 Forecast | N2: 2021 % Change | O2: 2022 % Change | P2: 2021 % Change | Q2: 2022 % Change | S2: Ratios | T2: Formula | U2: 2013 Actual | V2: 2014 Actual | W2: 2015 Actual | X2: 2016 Actual | Y2: 2017 Actual | Z2: 2018 Actual | AA2: 2019 Actual | AB2: 2020 Actual | AC2: 2021 Actual | AD2: 2022 Actual
A3: PROFIT AND LOSS STATEMENT | S3: Profitability Ratios
A4: Operating revenue | B4: 78380 | C4: 109256 | D4: 196439 | E4: 259738 | F4: 323190 | G4: 369086 | H4: 446739 | I4: 314395 | J4: 173492 | K4: 375327 | L4: =K4/$K$4 -> 1 | M4: =K4*1.05 -> 394093.35 | N4: =(J4-I4)/ABS(I4) -> -0.44817189 | O4: =(K4-J4)/ABS(J4) -> 1.1633678 | P4: =ABS(J4)/$J$4 -> 1 | Q4: =ABS(K4)/$K$4 -> 1 | S4: Return on Equity (ROE) | T4: Net Profit / Average Equity | V4: =C14/AVERAGE(B38:C38) -> 0.17315866 | W4: =D14/AVERAGE(C38:D38) -> 0.16504562 | X4: =E14/AVERAGE(D38:E38) -> 0.17550089 | Y4: =F14/AVERAGE(E38:F38) -> 0.17601179 | Z4: =G14/AVERAGE(F38:G38) -> 0.18595342 | AA4: =H14/AVERAGE(G38:H38) -> 0.17768479 | AB4: =I14/AVERAGE(H38:I38) -> 0.11284677 | AC4: =J14/AVERAGE(I38:J38) -> -0.045792114 | AD4: =K14/AVERAGE(J38:K38) -> 0.012841194
A5: Other revenue | B5: 383 | C5: 966 | D5: 1383 | E5: 4946 | F5: 2487 | G5: 3019 | H5: 2744 | I5: 35510 | J5: 26960 | K5: 13355 | L5: =K5/$K$4 -> 0.035582306 | M5: =L5*M4 -> 14022.75 | N5: =(J5-I5)/ABS(I5) -> -0.24077725 | O5: =(K5-J5)/ABS(J5) -> -0.5046365 | P5: =ABS(J5)/$J$4 -> 0.15539621 | Q5: =K5/$K$4 -> 0.035582306 | S5: Return on Assets (ROA) | T5: Net Profit / Average Total Assets | V5: =C14/AVERAGE(B29:C29) -> 0.096643451 | W5: =D14/AVERAGE(C29:D29) -> 0.08844869 | X5: =E14/AVERAGE(D29:E29) -> 0.088135727 | Y5: =F14/AVERAGE(E29:F29) -> 0.09040206 | Z5: =G14/AVERAGE(F29:G29) -> 0.10506047 | AA5: =H14/AVERAGE(G29:H29) -> 0.10452427 | AB5: =I14/AVERAGE(H29:I29) -> 0.073464127 | AC5: =J14/AVERAGE(I29:J29) -> -0.033984726 | AD5: =K14/AVERAGE(J29:K29) -> 0.0093911493
A6: Total revenue | B6: =B4+B5 -> 78763 | C6: =C4+C5 -> 110222 | D6: =D4+D5 -> 197822 | E6: =E4+E5 -> 264684 | F6: =F4+F5 -> 325677 | G6: =G4+G5 -> 372105 | H6: =H4+H5 -> 449483 | I6: =I4+I5 -> 349905 | ... K6: =K4+K5 -> 388682 | L6: =K6/$K$4 -> 1.0355823 | M6: =M4+M5 -> 408116.1 | N6: =(J6-I6)/ABS(I6) -> -0.42712451 | O6: =(K6-J6)/ABS(J6) -> 0.9390278 | P6: =ABS(J6)/$J$4 -> 1.1553962 | Q6: =K6/$K$4 -> 1.0355823 | S6: Profit Margin (PM) | T6: Net Profit / Sales Revenue | U6: =B14/B4 -> 0.14663179 | V6: =C14/C4 -> 0.16313978 | W6: =D14/D4 -> 0.1549285 | X6: =E14/E4 -> 0.17145354 | Y6: =F14/F4 -> 0.18325753 | Z6: =G14/G4 -> 0.21989184 | AA6: =H14/H4 -> 0.21159111 | AB6: =I14/I4 -> 0.20648865 | ... AD6: =K14/K4 -> 0.033064501
A7: Operating expenses | B7: -57765 | C7: -81360 | D7: -148727 | E7: -195654 | F7: -227062 | G7: -246655 | H7: -299101 | I7: -214683 | J7: -207619 | K7: -328775 | L7: =K7/$K$4 -> -0.87596949 | M7: =-(100000+(0.5*M4)) -> -297046.68 | N7: =(J7-I7)/ABS(I7) -> 0.032904329 | O7: =(K7-J7)/ABS(J7) -> -0.58354968 | P7: =ABS(J7)/$J$4 -> 1.1967065 | Q7: =K7/$K$4 -> -0.87596949 | S7: Efficiency Ratios
A8: Depreciation and amortisation | B8: -2079 | C8: -3599 | D8: -7540 | E8: -10562 | F8: -16157 | G8: -17833 | H8: -20348 | I8: -42512 | J8: -40857 | K8: -44423 | L8: =K8/$K$4 -> -0.11835813 | M8: =L8*M4 -> -46644.15 | N8: =(J8-I8)/ABS(I8) -> 0.038930184 | O8: =(K8-J8)/ABS(J8) -> -0.087280025 | P8: =ABS(J8)/$J$4 -> 0.23549789 | Q8: =K8/$K$4 -> -0.11835813 | S8: Asset Turnover Ratio (ATO) | T8: Sales Revenue / Average Total Assets | V8: =C4/AVERAGE(B29:C29) -> 0.59239659 | W8: =D4/AVERAGE(C29:D29) -> 0.57090005 | X8: =E4/AVERAGE(D29:E29) -> 0.5140502 | Y8: =F4/AVERAGE(E29:F29) -> 0.49330612 | Z8: =G4/AVERAGE(F29:G29) -> 0.47778247 | AA8: =H4/AVERAGE(G29:H29) -> 0.49399178 | AB8: =I4/AVERAGE(H29:I29) -> 0.35577803 | AC8: =J4/AVERAGE(I29:J29) -> 0.18269383 | AD8: =K4/AVERAGE(J29:K29) -> 0.28402513
A9: Total expenses | B9: =B7+B8 -> -59844 | C9: =C7+C8 -> -84959 | D9: =D7+D8 -> -156267 | E9: =E7+E8 -> -206216 | F9: =F7+F8 -> -243219 | G9: =G7+G8 -> -264488 | H9: =H7+H8 -> -319449 | I9: =I7+I8 -> -257195 | ... K9: =K7+K8 -> -373198 | L9: =K9/$K$4 -> -0.99432761 | M9: =M7+M8 -> -343690.83 | N9: =(J9-I9)/ABS(I9) -> 0.033900348 | O9: =(K9-J9)/ABS(J9) -> -0.50194787 | P9: =ABS(J9)/$J$4 -> 1.4322044 | Q9: =K9/$K$4 -> -0.99432761 | S9: Days in Receivables | T9: Average Accounts Receivable / Sales Revenue * 365 days | V9: =(AVERAGE(B21:C21)/C4)*365 -> 215.91613 | W9: =(AVERAGE(C21:D21)/D4)*365 -> 236.61203 | X9: =(AVERAGE(D21:E21)/E4)*365 -> 225.91558 | Y9: =(AVERAGE(E21:F21)/F4)*365 -> 208.56013 | Z9: =(AVERAGE(F21:G21)/G4)*365 -> 224.21354 | AA9: =(AVERAGE(G21:H21)/H4)*365 -> 237.35103 | AB9: =(AVERAGE(H21:I21)/I4)*365 -> 228.30625 | AC9: =(AVERAGE(I21:J21)/J4)*365 -> 252.42229 | AD9: =(AVERAGE(J21:K21)/K4)*365 -> 221.96491
A10: Profit before interest and tax (EBIT) | B10: =B6+B9 -> 18919 | C10: =C6+C9 -> 25263 | D10: =D6+D9 -> 41555 | E10: =E6+E9 -> 58468 | F10: =F6+F9 -> 82458 | G10: =G6+G9 -> 107617 | H10: =H6+H9 -> 130034 | I10: =I6+I9 -> 92710 | ... K10: =K6+K9 -> 15484 | L10: =K10/$K$4 -> 0.041254693 | M10: =M6+M9 -> 64425.275 | N10: =(J10-I10)/ABS(I10) -> -1.5180024 | O10: =(K10-J10)/ABS(J10) -> 1.3224221 | P10: =ABS(J10)/$J$4 -> 0.27680815 | Q10: =K10/$K$4 -> 0.041254693 | S10: Liquidity Analysis
A11: Interest expense | B11: -724 | C11: -640 | D11: -959 | E11: -1809 | F11: -3443 | G11: -3226 | H11: -2765 | I11: -9620 | J11: -3267 | K11: -2303 | L11: =K11/$K$4 -> -0.0061359828 | M11: -2303 | N11: =(J11-I11)/ABS(I11) -> 0.66039501 | O11: =(K11-J11)/ABS(J11) -> 0.29507193 | P11: =ABS(J11)/$J$4 -> 0.018830839 | Q11: =K11/$K$4 -> -0.0061359828 | S11: Current Ratio | T11: Current Assets / Current Liabilities | U11: =B24/B33 -> 1.3333754 | V11: =C24/C33 -> 1.2877966 | W11: =D24/D33 -> 1.2014342 | X11: =E24/E33 -> 1.071359 | Y11: =F24/F33 -> 1.0400407 | Z11: =G24/G33 -> 1.1693343 | AA11: =H24/H33 -> 1.2998744 | AB11: =I24/I33 -> 1.215564 | ... AD11: =K24/K33 -> 1.1639188
A12: Profit before tax | B12: =B10+B11 -> 18195 | C12: =C10+C11 -> 24623 | D12: =D10+D11 -> 40596 | E12: =E10+E11 -> 56659 | F12: =F10+F11 -> 79015 | G12: =G10+G11 -> 104391 | H12: =H10+H11 -> 127269 | I12: =I10+I11 -> 83090 | ... K12: =K10+K11 -> 13181 | L12: =K12/$K$4 -> 0.03511871 | M12: =M10+M11 -> 62122.275 | N12: =(J12-I12)/ABS(I12) -> -1.6172945 | O12: =(K12-J12)/ABS(J12) -> 1.2569847 | P12: =ABS(J12)/$J$4 -> 0.29563899 | Q12: =K12/$K$4 -> 0.03511871 | S12: Capital Structure Ratios
A13: Tax Expense | B13: -6702 | C13: -6799 | D13: -10162 | E13: -12126 | F13: -19788 | G13: -23232 | H13: -32743 | I13: -18171 | J13: 19018 | K13: -771 | L13: =K13/$K$4 -> -0.0020542087 | M13: =IF(M12>0,-1*30%*M12,0) -> -18636.682 | N13: =(J13-I13)/ABS(I13) -> 2.0466127 | O13: =(K13-J13)/ABS(J13) -> -1.0405405 | P13: =ABS(J13)/$J$4 -> 0.10961889 | Q13: =K13/$K$4 -> -0.0020542087 | S13: Debt to Equity (D/E) | T13: Total Liabilities / Total Equity | U13: =B37/B38 -> 0.65919024 | V13: =C37/C38 -> 0.86452094 | W13: =D37/D38 -> 0.86683961 | X13: =E37/E38 -> 1.0993317 | Y13: =F37/F38 -> 0.84391536 | Z13: =G37/G38 -> 0.70700881 | AA13: =H37/H38 -> 0.69431139 | AB13: =I37/I38 -> 0.36809673 | ... AD13: =K37/K38 -> 0.39373674
A14: Net profit (or loss) | B14: =B12+B13 -> 11493 | C14: =C12+C13 -> 17824 | D14: =D12+D13 -> 30434 | E14: =E12+E13 -> 44533 | F14: =F12+F13 -> 59227 | G14: =G12+G13 -> 81159 | H14: =H12+H13 -> 94526 | I14: =I12+I13 -> 64919 | ... K14: =K12+K13 -> 12410 | L14: =K14/$K$4 -> 0.033064501 | M14: =M12+M13 -> 43485.592 | N14: =(J14-I14)/ABS(I14) -> -1.4971272 | O14: =(K14-J14)/ABS(J14) -> 1.384532 | P14: =ABS(J14)/$J$4 -> 0.1860201 | Q14: =K14/$K$4 -> 0.033064501 | S14: Debt to Assets | T14: Total Liabilities / Total Assets | U14: =B37/B29 -> 0.39729636 | V14: =C37/C29 -> 0.4636692 | W14: =D37/D29 -> 0.46433534 | X14: =E37/E29 -> 0.52365793 | Y14: =F37/F29 -> 0.45767576 | Z14: =G37/G29 -> 0.41417994 | AA14: =H37/H29 -> 0.40978972 | AB14: =I37/I29 -> 0.26905753 | ... AD14: =K37/K29 -> 0.28250438
S15: Equity Ratio | T15: Total Equity / Total Assets | U15: =B38/B29 -> 0.60270364 | V15: =C38/C29 -> 0.5363308 | W15: =D38/D29 -> 0.53566466 | X15: =E38/E29 -> 0.47634207 | Y15: =F38/F29 -> 0.54232424 | Z15: =G38/G29 -> 0.58582006 | AA15: =H38/H29 -> 0.59021028 | AB15: =I38/I29 -> 0.73094247 | ... AD15: =K38/K29 -> 0.71749562
A16: Dividends paid | B16: -7497 | C16: -9129 | D16: -13523 | E16: -20983 | F16: -30514 | G16: -37471 | H16: -45271 | I16: -26456 | J16: 0 | K16: 0 | M16: =M4*5% -> 19704.668 | N16: - | O16: - | P16: =ABS(J16)/$J$4 -> 0 | Q16: =ABS(K16)/$J$4 -> 0 | S16: Interest Coverage Ratio | T16: (Net Profit + Interest Expense + Tax Expense) / Interest Expense | U16: =(B14+B11+B13)/ABS(B11) -> 5.6174033 | V16: =(C14+C11+C13)/ABS(C11) -> 16.226562 | W16: =(D14+D11+D13)/ABS(D11) -> 20.138686 | X16: =(E14+E11+E13)/ABS(E11) -> 16.914317 | Y16: =(F14+F11+F13)/ABS(F11) -> 10.454836 | Z16: =(G14+G11+G13)/ABS(G11) -> 16.956293 | AA16: =(H14+H11+H13)/ABS(H11) -> 21.344665 | AB16: =(I14+I11+I13)/ABS(I11) -> 3.8594595 | ... AD16: =(K14+K11+K13)/ABS(K11) -> 4.0538428
S17: Market Performance Analysis
B18: 2013 Actual | C18: 2014 Actual | D18: 2015 Actual | E18: 2016 Actual | F18: 2017 Actual | G18: 2018 Actual | H18: 2019 Actual | I18: 2020 Actual | J18: 2021 Actual | K18: 2022 Actual | L18: Percentage | M18: 2023 Forecast | N18: 2021 % Change | O18: 2022 % Change | P18: 2021 % Change | Q18: 2022 % Change | S18: Market to Book Ratio (M/B) | T18: Current Market Capitalisation / Net Assets | U18: =B40/B29 -> 2.472336 | V18: =C40/C29 -> 2.2339313 | W18: =D40/D29 -> 2.1950101 | X18: =E40/E29 -> 2.3281364 | Y18: =F40/F29 -> 3.1685525 | Z18: =G40/G29 -> 3.4969516 | AA18: =H40/H29 -> 2.3626462 | AB18: =I40/I29 -> 1.3440696 | ... AD18: =K40/K29 -> 1.7840968
A19: BALANCE SHEET | S19: DuPont Analysis | T19: ROE = PM * ATO * Leverage
A20: Cash | B20: 13535 | C20: 32000 | D20: 40663 | E20: 81178 | F20: 79217 | G20: 84297 | H20: 138791 | I20: 92843 | J20: 99018 | K20: 142054 | L20: =K20/$K$4 -> 0.37848063 | M20: =L20*$M$4 -> 149156.7 | N20: =(J20-I20)/ABS(I20) -> 0.06651013 | O20: =(K20-J20)/ABS(J20) -> 0.43462805 | P20: =J20/$J$29 -> 0.087183072 | Q20: =K20/$K$29 -> 0.094252392 | S20: Profit Margin (PM) | T20: Net Profit / Sales Revenue | U20: =B14/B4 -> 0.14663179 | V20: =C14/C4 -> 0.16313978 | W20: =D14/D4 -> 0.1549285 | X20: =E14/E4 -> 0.17145354 | Y20: =F14/F4 -> 0.18325753 | Z20: =G14/G4 -> 0.21989184 | AA20: =H14/H4 -> 0.21159111 | AB20: =I14/I4 -> 0.20648865 | ... AD20: =K14/K4 -> 0.033064501
A21: Accounts receivables | B21: 27975 | C21: 101286 | D21: 153398 | E21: 168130 | F21: 201210 | G21: 252237 | H21: 328771 | I21: 64535 | J21: 175428 | K21: 281062 | L21: =K21/$K$4 -> 0.74884567 | M21: =L21*$M$4 -> 295115.1 | N21: =(J21-I21)/ABS(I21) -> 1.7183389 | O21: =(K21-J21)/ABS(J21) -> 0.60215017 | P21: =J21/$J$29 -> 0.15446032 | Q21: =K21/$K$29 -> 0.18648377 | S21: Asset Turnover Ratio (ATO) | T21: Sales Revenue / Average Total Assets | V21: =C4/AVERAGE(B29:C29) -> 0.59239659 | W21: =D4/AVERAGE(C29:D29) -> 0.57090005 | X21: =E4/AVERAGE(D29:E29) -> 0.5140502 | Y21: =F4/AVERAGE(E29:F29) -> 0.49330612 | Z21: =G4/AVERAGE(F29:G29) -> 0.47778247 | AA21: =H4/AVERAGE(G29:H29) -> 0.49399178 | AB21: =I4/AVERAGE(H29:I29) -> 0.35577803 | AC21: =J4/AVERAGE(I29:J29) -> 0.18269383 | AD21: =K4/AVERAGE(J29:K29) -> 0.28402513
A22: Inventories | B22: 0 | C22: 0 | D22: 0 | E22: 0 | F22: 0 | G22: 0 | H22: 0 | I22: 0 | J22: 884 | K22: 1422 | L22: =K22/$K$4 -> 0.0037886963 | M22: =L22*$M$4 -> 1493.1 | N22: - | O22: =(K22-J22)/ABS(J22) -> 0.60859729 | P22: =J22/$J$29 -> 0.00077834167 | Q22: =K22/$K$29 -> 0.00094349262 | S22: Leverage | T22: Average Total Assets / Average Equity | V22: =AVERAGE(B29:C29)/AVERAGE(B38:C38) -> 1.7917268 | W22: =AVERAGE(C29:D29)/AVERAGE(C38:D38) -> 1.8660041 | X22: =AVERAGE(D29:E29)/AVERAGE(D38:E38) -> 1.9912571 | Y22: =AVERAGE(E29:F29)/AVERAGE(E38:F38) -> 1.9469887 | Z22: =AVERAGE(F29:G29)/AVERAGE(F38:G38) -> 1.7699657 | AA22: =AVERAGE(G29:H29)/AVERAGE(G38:H38) -> 1.6999382 | AB22: =AVERAGE(H29:I29)/AVERAGE(H38:I38) -> 1.53608 | AC22: =AVERAGE(I29:J29)/AVERAGE(I38:J38) -> 1.3474322 | AD22: =AVERAGE(J29:K29)/AVERAGE(J38:K38) -> 1.367372
A23: Other current assets | B23: 706 | C23: 1979 | D23: 4643 | E23: 4918 | F23: 4462 | G23: 4203 | H23: 10576 | I23: 16444 | J23: 15344 | K23: 17033 | L23: =K23/$K$4 -> 0.04538176 | M23: =L23*$M$4 -> 17884.65 | N23: =(J23-I23)/ABS(I23) -> -0.0668937 | O23: =(K23-J23)/ABS(J23) -> 0.1100756 | P23: =J23/$J$29 -> 0.013510039 | Q23: =K23/$K$29 -> 0.011301343 | S23: Return on Equity (ROE) | T23: ROE = PM * ATO * Leverage | V23: =V20*V21*V22 -> 0.17315866 | W23: =W20*W21*W22 -> 0.16504562 | X23: =X20*X21*X22 -> 0.17550089 | Y23: =Y20*Y21*Y22 -> 0.17601179 | Z23: =Z20*Z21*Z22 -> 0.18595342 | AA23: =AA20*AA21*AA22 -> 0.17768479 | AB23: =AB20*AB21*AB22 -> 0.11284677 | AC23: =AC20*AC21*AC22 -> -0.045792114 | AD23: =AD20*AD21*AD22 -> 0.012841194
A24: Total current assets | B24: =B20+B21+B22+B23 -> 42216 | C24: =C20+C21+C22+C23 -> 135265 | D24: =D20+D21+D22+D23 -> 198704 | E24: =E20+E21+E22+E23 -> 254226 | F24: =F20+F21+F22+F23 -> 284889 | G24: =G20+G21+G22+G23 -> 340737 | H24: =H20+H21+H22+H23 -> 478138 | I24: =I20+I21+I22+I23 -> 173822 | ... K24: =K20+K21+K22+K23 -> 441571 | L24: =K24/$K$4 -> 1.1764968 | M24: =M20+M21+M22+M23 -> 463649.55 | N24: =(J24-I24)/ABS(I24) -> 0.67225092 | O24: =(K24-J24)/ABS(J24) -> 0.51912796 | P24: =J24/$J$29 -> 0.25593177 | Q24: =K24/$K$29 -> 0.292981
A25: Fixed assets | B25: 3166 | C25: 3371 | D25: 3697 | E25: 5426 | F25: 5262 | G25: 6118 | H25: 13328 | I25: 58919 | J25: 51681 | K25: 54014 | L25: =K25/$K$4 -> 0.14391184 | M25: =L25*$M$4 -> 56714.7 | N25: =(J25-I25)/ABS(I25) -> -0.12284662 | O25: =(K25-J25)/ABS(J25) -> 0.045142315 | P25: =J25/$J$29 -> 0.045503932 | Q25: =K25/$K$29 -> 0.035838123
A26: Goodwill | B26: 72876 | C26: 94260 | D26: 215555 | E26: 280107 | F26: 393238 | G26: 407187 | H26: 453522 | I26: 478211 | J26: 0 | K26: 859193 | L26: =K26/$K$4 -> 2.2891852 | M26: =L26*$M$4 -> 902152.65 | N26: =(J26-I26)/ABS(I26) -> -1 | O26: - | P26: =J26/$J$29 -> 0 | Q26: =K26/$K$29 -> 0.57007191
A27: Other non-current assets | B27: 2838 | C27: 14869 | D27: 22452 | E27: 30388 | F27: 56766 | G27: 50799 | H27: 58861 | I27: 52565 | J27: 793393 | K27: 152388 | L27: =K27/$K$4 -> 0.40601396 | M27: =L27*$M$4 -> 160007.4 | N27: =(J27-I27)/ABS(I27) -> 14.09356 | O27: =(K27-J27)/ABS(J27) -> -0.80792873 | P27: =J27/$J$29 -> 0.69856429 | Q27: =K27/$K$29 -> 0.10110897
A28: Total non-current assets | B28: =B25+B26+B27 -> 78880 | C28: =C25+C26+C27 -> 112500 | D28: =D25+D26+D27 -> 241704 | E28: =E25+E26+E27 -> 315921 | F28: =F25+F26+F27 -> 455266 | G28: =G25+G26+G27 -> 464104 | H28: =H25+H26+H27 -> 525711 | I28: =I25+I26+I27 -> 589695 | ... K28: =K25+K26+K27 -> 1065595 | L28: =K28/$K$4 -> 2.839111 | M28: =M25+M26+M27 -> 1118874.8 | N28: =(J28-I28)/ABS(I28) -> 0.43306964 | O28: =(K28-J28)/ABS(J28) -> 0.26094875 | P28: =J28/$J$29 -> 0.74406823 | Q28: =K28/$K$29 -> 0.707019
A29: Total assets | B29: =B24+B28 -> 121096 | C29: =C24+C28 -> 247765 | D29: =D24+D28 -> 440408 | E29: =E24+E28 -> 570147 | F29: =F24+F28 -> 740155 | G29: =G24+G28 -> 804841 | H29: =H24+H28 -> 1003849 | I29: =I24+I28 -> 763517 | ... K29: =K24+K28 -> 1507166 | L29: =K29/$K$4 -> 4.0156077 | M29: =M24+M28 -> 1582524.3 | N29: =(J29-I29)/ABS(I29) -> 0.48752156 | O29: =(K29-J29)/ABS(J29) -> 0.32702501 | P29: =J29/$J$29 -> 1 | Q29: =K29/$K$29 -> 1
A30: Account payable | B30: 26048 | C30: 94126 | D30: 148385 | E30: 202720 | F30: 233049 | G30: 253621 | H30: 316753 | I30: 100499 | J30: 204745 | K30: 341467 | L30: =K30/$K$4 -> 0.90978533 | M30: =L30*$M$4 -> 358540.35 | N30: =(J30-I30)/ABS(I30) -> 1.037284 | O30: =(K30-J30)/ABS(J30) -> 0.66776722 | P30: =J30/$J$37 -> 0.72019515 | Q30: =K30/$K$37 -> 0.80197801
A31: Short-term debt | B31: 3192 | C31: 0 | D31: 0 | E31: 14347 | F31: 18122 | G31: 14677 | H31: 19205 | I31: 8672 | J31: 9193 | K31: 10751 | L31: =K31/$K$4 -> 0.028644355 | M31: =L31*$M$4 -> 11288.55 | N31: =(J31-I31)/ABS(I31) -> 0.060078413 | O31: =(K31-J31)/ABS(J31) -> 0.16947678 | P31: =J31/$J$37 -> 0.032336585 | Q31: =K31/$K$37 -> 0.02525007
A32: Other current liabilities | B32: 2421 | C32: 10910 | D32: 17004 | E32: 20226 | F32: 22750 | G32: 23096 | H32: 31876 | I32: 33826 | J32: 18155 | K32: 27165 | L32: =K32/$K$4 -> 0.072376887 | M32: =L32*$M$4 -> 28523.25 | N32: =(J32-I32)/ABS(I32) -> -0.46328268 | O32: =(K32-J32)/ABS(J32) -> 0.49628202 | P32: =J32/$J$37 -> 0.063860622 | Q32: =K32/$K$37 -> 0.063800404
A33: Total current liabilities | B33: =B30+B31+B32 -> 31661 | C33: =C30+C31+C32 -> 105036 | D33: =D30+D31+D32 -> 165389 | E33: =E30+E31+E32 -> 237293 | F33: =F30+F31+F32 -> 273921 | G33: =G30+G31+G32 -> 291394 | H33: =H30+H31+H32 -> 367834 | I33: =I30+I31+I32 -> 142997 | ... K33: =K30+K31+K32 -> 379383 | L33: =K33/$K$4 -> 1.0108066 | M33: =M30+M31+M32 -> 398352.15 | N33: =(J33-I33)/ABS(I33) -> 0.62306202 | O33: =(K33-J33)/ABS(J33) -> 0.6346163 | P33: =J33/$J$37 -> 0.81639236 | Q33: =K33/$K$37 -> 0.89102849
A34: Long-term debt | B34: 157 | C34: 0 | D34: 0 | E34: 22833 | F34: 27301 | G34: 29301 | H34: 20085 | I34: 44423 | J34: 37188 | K34: 37601 | L34: =K34/$K$4 -> 0.10018197 | M34: =L34*$M$4 -> 39481.05 | N34: =(J34-I34)/ABS(I34) -> -0.16286608 | O34: =(K34-J34)/ABS(J34) -> 0.011105733 | P34: =J34/$J$37 -> 0.13080963 | Q34: =K34/$K$37 -> 0.088310657
A35: Other non-current liabilities | B35: 16293 | C35: 9845 | D35: 39108 | E35: 38436 | F35: 37529 | G35: 12654 | H35: 23448 | I35: 18010 | J35: 15010 | K35: 8797 | L35: =K35/$K$4 -> 0.023438229 | M35: =L35*$M$4 -> 9236.85 | N35: =(J35-I35)/ABS(I35) -> -0.16657413 | O35: =(K35-J35)/ABS(J35) -> -0.41392405 | P35: =J35/$J$37 -> 0.052798013 | Q35: =K35/$K$37 -> 0.020660856
A36: Total non-current liabilities | B36: =B34+B35 -> 16450 | C36: =C34+C35 -> 9845 | D36: =D34+D35 -> 39108 | E36: =E34+E35 -> 61269 | F36: =F34+F35 -> 64830 | G36: =G34+G35 -> 41955 | H36: =H34+H35 -> 43533 | I36: =I34+I35 -> 62433 | ... K36: =K34+K35 -> 46398 | L36: =K36/$K$4 -> 0.1236202 | M36: =M34+M35 -> 48717.9 | N36: =(J36-I36)/ABS(I36) -> -0.16393574 | O36: =(K36-J36)/ABS(J36) -> -0.11111537 | P36: =J36/$J$37 -> 0.18360764 | Q36: =K36/$K$37 -> 0.10897151
A37: Total liabilities | B37: =B36+B33 -> 48111 | C37: =C36+C33 -> 114881 | D37: =D36+D33 -> 204497 | E37: =E36+E33 -> 298562 | F37: =F36+F33 -> 338751 | G37: =G36+G33 -> 333349 | H37: =H36+H33 -> 411367 | I37: =I36+I33 -> 205430 | ... K37: =K36+K33 -> 425781 | L37: =K37/$K$4 -> 1.1344268 | M37: =M36+M33 -> 447070.05 | N37: =(J37-I37)/ABS(I37) -> 0.38388259 | O37: =(K37-J37)/ABS(J37) -> 0.49769426 | P37: =J37/$J$37 -> 1 | Q37: =K37/$K$37 -> 1
A38: Owners' equity | B38: =B29-B37 -> 72985 | C38: =C29-C37 -> 132884 | D38: =D29-D37 -> 235911 | E38: =E29-E37 -> 271585 | F38: =F29-F37 -> 401404 | G38: =G29-G37 -> 471492 | H38: =H29-H37 -> 592482 | I38: =I29-I37 -> 558087 | ... K38: =K29-K37 -> 1081385 | L38: =K38/$K$4 -> 2.8811809 | M38: =L38*$M$4 -> 1135454.3 | N38: =(J38-I38)/ABS(I38) -> 0.52567073 | O38: =(K38-J38)/ABS(J38) -> 0.27004065 | P38: =J38/J38 -> 1 | Q38: =K38/K38 -> 1
A40: Market capitalisation | B40: 299390 | C40: 553490 | D40: 966700 | E40: 1327380 | F40: 2345220 | G40: 2814490 | H40: 2371740 | I40: 1026220 | J40: 2931780 | K40: 2688930 | N40: =(J40-I40)/I40 -> 1.8568728 | O40: =(K40-J40)/J40 -> -0.082833637

Sheet The O'Riordan Investment
C2: Year
C3: 0 | D3: 1 | E3: 2 | F3: 3 | G3: 4 | H3: 5 | I3: 6 | J3: 7 | K3: 8 | L3: 9 | M3: 10
B5: Fixed assets | C5: -13200000 | M5: =16000000 -> 16000000
B6: Net working capital | D6: -300000 | E6: =(-10%*E9)-D6 -> -100000 | M6: 400000
B7: ‘Investment’ | C7: =SUM(C5:C6) -> -13200000 | D7: =SUM(D5:D6) -> -300000 | E7: =SUM(E5:E6) -> -100000 | F7: =SUM(F5:F6) -> 0 | G7: =SUM(G5:G6) -> 0 | H7: =SUM(H5:H6) -> 0 | I7: =SUM(I5:I6) -> 0 | J7: =SUM(J5:J6) -> 0 | ... M7: =SUM(M5:M6) -> 16400000
B9: Change in Operating revenues | D9: 3000000 | E9: 4000000 | F9: =(E9*1.05)-E9 -> 200000 | G9: =F9*1.05 -> 210000 | H9: =G9*1.05 -> 220500 | I9: =H9*1.05 -> 231525 | J9: =I9*1.05 -> 243101.25 | K9: =J9*1.05 -> 255256.31 | L9: =K9*1.05 -> 268019.13 | M9: =L9*1.05 -> 281420.08
B10: Change in Operating expenses | D10: =-45%*D9 -> -1350000 | E10: =-45%*E9 -> -1800000 | F10: =-45%*F9 -> -90000 | G10: =-45%*G9 -> -94500 | H10: =-45%*H9 -> -99225 | I10: =-45%*I9 -> -104186.25 | J10: =-45%*J9 -> -109395.56 | K10: =-45%*K9 -> -114865.34 | ... M10: =-45%*M9 -> -126639.04
B11: Operating income | D11: =D9+D10 -> 1650000 | E11: =E9+E10 -> 2200000 | F11: =F9+F10 -> 110000 | G11: =G9+G10 -> 115500 | H11: =H9+H10 -> 121275 | I11: =I9+I10 -> 127338.75 | J11: =J9+J10 -> 133705.69 | K11: =K9+K10 -> 140390.97 | ... M11: =M9+M10 -> 154781.05
B13: Depreciation | D13: =$F$27 -> -300000 | E13: =$F$27 -> -300000 | F13: =$F$27 -> -300000 | G13: =$F$27 -> -300000 | H13: =$F$27 -> -300000 | I13: =$F$27 -> -300000 | J13: =$F$27 -> -300000 | K13: =$F$27 -> -300000 | ... M13: =$F$27 -> -300000
B14: Interest expense | D14: 0 | E14: 0 | F14: 0 | G14: 0 | H14: 0 | I14: 0 | J14: 0 | K14: 0 | L14: 0 | M14: 0
B15: Profit before tax | D15: =D11+D13+D14 -> 1350000 | E15: =E11+E13+E14 -> 1900000 | F15: =F11+F13+F14 -> -190000 | G15: =G11+G13+G14 -> -184500 | H15: =H11+H13+H14 -> -178725 | I15: =I11+I13+I14 -> -172661.25 | J15: =J11+J13+J14 -> -166294.31 | K15: =K11+K13+K14 -> -159609.03 | ... M15: =M11+M13+M14 -> -145218.95
B17: Tax expense (@30%) | D17: =D15*-1*30% -> -405000 | E17: =E15*-1*30% -> -570000 | F17: 0 | G17: 0 | H17: 0 | I17: 0 | J17: 0 | K17: 0 | L17: 0 | M17: =(M15*0.3)+(F29-M5)*0.3 -> -1783565.7 | N17: Note that the tax expense in the final year should include any extra tax (or tax deduction) from the sale of the fixed assets
B18: Net profit after tax | D18: =D15+D17 -> 945000 | E18: =E15+E17 -> 1330000 | F18: =F15+F17 -> -190000 | G18: =G15+G17 -> -184500 | H18: =H15+H17 -> -178725 | I18: =I15+I17 -> -172661.25 | J18: =J15+J17 -> -166294.31 | K18: =K15+K17 -> -159609.03 | ... M18: =M15+M17 -> -1928784.6
B20: Add back depreciation | D20: =-D13 -> 300000 | E20: =-E13 -> 300000 | F20: =-F13 -> 300000 | G20: =-G13 -> 300000 | H20: =-H13 -> 300000 | I20: =-I13 -> 300000 | J20: =-J13 -> 300000 | K20: =-K13 -> 300000 | ... M20: =-M13 -> 300000
B21: After-tax cash flow | D21: =D18+D20 -> 1245000 | E21: =E18+E20 -> 1630000 | F21: =F18+F20 -> 110000 | G21: =G18+G20 -> 115500 | H21: =H18+H20 -> 121275 | I21: =I18+I20 -> 127338.75 | J21: =J18+J20 -> 133705.69 | K21: =K18+K20 -> 140390.97 | ... M21: =M18+M20 -> -1628784.6
B23: Free cash flow | C23: =C7 -> -13200000 | D23: =D21+D7 -> 945000 | E23: =E21+E7 -> 1530000 | F23: =F21+F7 -> 110000 | G23: =G21+G7 -> 115500 | H23: =H21+H7 -> 121275 | I23: =I21+I7 -> 127338.75 | J23: =J21+J7 -> 133705.69 | K23: =K21+K7 -> 140390.97 | ... M23: =M21+M7 -> 14771215
B25: Discount rate = | C25: ='Historical Data'!J14 -> 0.1150578
B27: NPV = | C27: =NPV(C25,D23:M23)+C23 -> -5683884.3 | E27: Annual Depreciation | F27: =-D9/10 -> -300000
B28: PI = | C28: =(C27+-C7)/-C7 -> 0.5694027 | E28: Accumulated Depreciation | F28: =F27*-10 -> 3000000
B29: IRR = | C29: =IRR(C23:M23) -> 0.038152513 | E29: Book Vaue | F29: =13200000-F28 -> 10200000

Sheet Historical Data
C2: Price | E2: Weekly Return
B3: Date | C3: FTL | D3: AORD | E3: FTL | F3: AORD | H3: E | I3: Market value of equity = | J3: ='Footloose Financial Statements'!K40 -> 2688930 | L3: Given Information
B4: 44746 | C4: 19.55 | D4: 6877 | H4: D | I4: Market value of debt = | J4: =('Footloose Financial Statements'!O16+'Footloose Financial Statements'!O17) -> 50769.6 | L4: Market Value of Equity= | M4: ='Footloose Financial Statements'!K40 -> 2688930
B5: 44753 | C5: 17.91 | D5: 6798 | E5: =(C5-C4)/C4 -> -0.083887468 | F5: =(D5-D4)/D4 -> -0.011487567 | L5: Market Value of Debt= | M5: =J4 -> 50769.6
B6: 44760 | C6: 18.13 | D6: 7011.8 | E6: =(C6-C5)/C5 -> 0.01228364 | F6: =(D6-D5)/D5 -> 0.031450427 | H6: r_F | I6: Risk-free rate = | J6: 0.04249 | L6: Contracted coupon rate= | M6: 0.0625
B7: 44767 | C7: 18.71 | D7: 7173.8 | E7: =(C7-C6)/C6 -> 0.031991175 | F7: =(D7-D6)/D6 -> 0.023103911 | H7: MRP | I7: Market risk-premium = | J7: 0.055 | L7: Coupon payment frequency= | M7: 2 per year
B8: 44774 | C8: 20.54 | D8: 7250.3 | E8: =(C8-C7)/C7 -> 0.097808658 | F8: =(D8-D7)/D7 -> 0.010663804 | H8: beta | I8: Equity beta = | J8: =SLOPE(E5:E56,F5:F56) -> 1.3428671 | L8: Current market price (as of 20 July 2023)= | M8: 92.78
B9: 44781 | C9: 20.68 | D9: 7288.8 | E9: =(C9-C8)/C8 -> 0.0068159688 | F9: =(D9-D8)/D8 -> 0.0053101251 | H9: t | I9: Corporate tax rate = | J9: 0.3 | L9: Maturity Date= | M9: 17 August, 2027
B10: 44788 | C10: 19.98 | D10: 7358.7 | E10: =(C10-C9)/C9 -> -0.03384913 | F10: =(D10-D9)/D9 -> 0.009590056
B11: 44795 | C11: 18.89 | D11: 7345.8 | E11: =(C11-C10)/C10 -> -0.054554555 | F11: =(D11-D10)/D10 -> -0.001753027 | H11: K_E | I11: Cost of equity = | J11: =J6+J8*J7 -> 0.11634769 | L11: Calculated Information
B12: 44802 | C12: 19.04 | D12: 7056.3 | E12: =(C12-C11)/C11 -> 0.0079407094 | F12: =(D12-D11)/D11 -> -0.039410275 | H12: K_D | I12: (pre-tax) Cost of debt = | J12: =M12*(1-J9) -> 0.066773 | L12: Yield to Maturity % | M12: 0.09539
B13: 44809 | C13: 19.14 | D13: 7139 | E13: =(C13-C12)/C12 -> 0.0052521008 | F13: =(D13-D12)/D12 -> 0.011720023 | L13: Annual Equivalent Rate % | M13: 0.09767
B14: 44816 | C14: 19.06 | D14: 6975.2 | E14: =(C14-C13)/C13 -> -0.0041797283 | F14: =(D14-D13)/D13 -> -0.02294439 | I14: WACC = | J14: =((1-J9)*J12*J4+J11*J3)/(J3+J4) -> 0.1150578 | L14: Accrued Interest $ | M14: 0.87
B15: 44823 | C15: 17.58 | D15: 6788.7 | E15: =(C15-C14)/C14 -> -0.077649528 | F15: =(D15-D14)/D14 -> -0.026737585
B16: 44830 | C16: 16.68 | D16: 6678.7 | E16: =(C16-C15)/C15 -> -0.051194539 | F16: =(D16-D15)/D15 -> -0.016203397
B17: 44837 | C17: 17.03 | D17: 6976.1 | E17: =(C17-C16)/C16 -> 0.020983213 | F17: =(D17-D16)/D16 -> 0.044529624
B18: 44844 | C18: 16.51 | D18: 6948.6 | E18: =(C18-C17)/C17 -> -0.030534351 | F18: =(D18-D17)/D17 -> -0.0039420306
B19: 44851 | C19: 16.68 | D19: 6869.9 | E19: =(C19-C18)/C18 -> 0.01029679 | F19: =(D19-D18)/D18 -> -0.011326023
B20: 44858 | C20: 16.83 | D20: 6973.5 | E20: =(C20-C19)/C19 -> 0.0089928058 | F20: =(D20-D19)/D19 -> 0.015080278
B21: 44865 | C21: 17.5 | D21: 7089.3 | E21: =(C21-C20)/C20 -> 0.039809863 | F21: =(D21-D20)/D20 -> 0.016605722
B22: 44872 | C22: 18.23 | D22: 7350.1 | E22: =(C22-C21)/C21 -> 0.041714286 | F22: =(D22-D21)/D21 -> 0.036787835
B23: 44879 | C23: 16.86 | D23: 7354.7 | E23: =(C23-C22)/C22 -> -0.07515085 | F23: =(D23-D22)/D22 -> 0.00062584183
B24: 44886 | C24: 16.79 | D24: 7447.6 | E24: =(C24-C23)/C23 -> -0.0041518387 | F24: =(D24-D23)/D23 -> 0.012631379
B25: 44893 | C25: 15.39 | D25: 7503.5 | E25: =(C25-C24)/C24 -> -0.083382966 | F25: =(D25-D24)/D24 -> 0.0075057737
B26: 44900 | C26: 14.04 | D26: 7406.3 | E26: =(C26-C25)/C25 -> -0.087719298 | F26: =(D26-D25)/D25 -> -0.012953955
... B56: 45110 | C56: 18.03 | D56: 7244.1 | E56: =(C56-C55)/C55 -> 0.0078256009 | F56: =(D56-D55)/D55 -> -0.02126596

Sheet Option to Abandon
C2: Year
C3: 0 | D3: 1 | E3: 2 | F3: 3
B5: Fixed assets | C5: -13200000 | F5: =16000000 -> 16000000
B6: Net working capital | D6: -300000 | E6: =(-10%*E9)-D6 -> -100000 | F6: 400000
B7: ‘Investment’ | C7: =SUM(C5:C6) -> -13200000 | D7: =SUM(D5:D6) -> -300000 | E7: =SUM(E5:E6) -> -100000 | F7: =SUM(F5:F6) -> 16400000
B9: Change in Operating revenues | D9: 3000000 | E9: 4000000 | F9: 4000001
B10: Change in Operating expenses | D10: =-45%*D9 -> -1350000 | E10: =-45%*E9 -> -1800000 | F10: =-45%*F9 -> -1800000.4
B11: Operating income | D11: =D9+D10 -> 1650000 | E11: =E9+E10 -> 2200000 | F11: =F9+F10 -> 2200000.5
B13: Depreciation | D13: =$F$27 -> -150000 | E13: =$F$27 -> -150000 | F13: =$F$27 -> -150000
B14: Interest expense | D14: 0 | E14: 0 | F14: 1
B15: Profit before tax | D15: =D11+D13+D14 -> 1500000 | E15: =E11+E13+E14 -> 2050000 | F15: =F11+F13+F14 -> 2050001.5
B17: Tax expense (@30%) | D17: =D15*-1*30% -> -450000 | E17: =E15*-1*30% -> -615000 | F17: =(F15*0.3)+(F29-F5)*0.3 -> -674999.54 | G17: Note that the tax expense in the final year should include any extra tax (or tax deduction) from the sale of the fixed assets
B18: Net profit after tax | D18: =D15+D17 -> 1050000 | E18: =E15+E17 -> 1435000 | F18: =F15+F17 -> 1375002
B20: Add back depreciation | D20: =-D13 -> 150000 | E20: =-E13 -> 150000 | F20: =-F13 -> 150000
B21: After-tax cash flow | D21: =D18+D20 -> 1200000 | E21: =E18+E20 -> 1585000 | F21: =F18+F20 -> 1525002
B23: Free cash flow | C23: =C7 -> -13200000 | D23: =D21+D7 -> 900000 | E23: =E21+E7 -> 1485000 | F23: =F21+F7 -> 17925002
B25: Discount rate = | C25: ='Historical Data'!J14 -> 0.1150578
B27: NPV = | C27: =NPV(C25,D23:F23)+C23 -> 1730546.8 | E27: Annual Depreciation | F27: =-D9/20 -> -150000
B28: PI = | C28: =(C27+-C7)/-C7 -> 1.131102 | E28: Accumulated Depreciation | F28: =F27*-10 -> 1500000
B29: IRR = | C29: =IRR(C23:F23) -> 0.16510212 | E29: Book Vaue | F29: =13200000-F28 -> 11700000
