Workbook

Sheet Customer 1
A1: Loan Application | E1: Information
A2: File Number | B2: 11
A3: Customer Number | B3: 1
E4: Student Bank Loan application form
A5: Identifying Information | C5: Comments | E5: Loan details
A6: Customer number and name | B6: =E9 -> Kastanas, Sean | E6: Amount requested | F6: Loan Type | G6: Individual Or Join Cr | H6: Secured Offered | I6: For How Long | J6: Proceeds of loan to be used for
A7: Age | B7: =DATEDIF(DATE(1994,4,1), DATE(2025,8,1), "Y") -> 31 | E7: 9500 | F7: motorcycle | G7: Individual | H7: motorcycle | I7: 4 | J7: buy new Honda motorcycle for $13,000
A8: Student Bank’s credit score | B8: 170 - Reject | C8: Reject loan application. We considered the applicant's job as a skilled traadesperson. | E8: Customer Name | F8: Birthdate | G8: Status | H8: No of children | I8: current home own/rent how long | K8: previous home own/rent how long
A9: Other banks’ credit score | B9: =G36 -> 0 | C9: Not Given | E9: Kastanas, Sean | F9: 34425 | G9: Single | I9: at home | J9: rent room | K9: at home
A10: Gross wage income (yearly) | B10: =F47 -> 50960 | E10: Employer | F10: Position | G10: Years at employer | H10: Gross Wage | I10: Previous employer and years service | K10: Credit rating | L10: Do you bank with us (details)
A11: Dividend and rental income (yearly) | B11: 0 | C11: Not Given | E11: Wind Eldercare | F11: landscaping | G11: 4 | H11: 50960 | K11: none | L11: no
A12: Total income | B12: =B10+B11 -> 50960 | E12: Joint borrower details
E13: Customer Name | F13: Birthdate | G13: Status | H13: No of children | I13: current home own/rent how long | K13: previous home own/rent how long
A14: Loan Information
A15: Loan amount | B15: =E7 -> 9500 | E15: Employer | F15: Position | G15: Years at employer | H15: Gross Wage | I15: Previous employer and years service | K15: Credit rating | L15: Do you bank with us (details)
A16: Reason for loan | B16: buy new Honda motorcycle for $13,000
A17: Deposit amount | B17: =13000-9500 -> 3500 | E17: Statement of Financial position (your assets and Liabilities)
A18: Deposit % of purchase price | B18: =(13000-9500)/13000 -> 0.26923077 | C18: Greater than 20% minimum deposit is required | E18: List of assets | I18: balance /estimated value
A19: Loan term | B19: 4 | C19: As per policy maximum allowable Loan period is 3 years as opposed to the requested 4 years. From FAQ, If the loan term requested exceeds the maximum term allowed, the loan application will be rejected. Loan officers need to apply the maximum term allowed by the Student Bank loan policy to calculate monthly repayments. | E19: other bank savings account | I19: 3280
A20: Loan rate in % per annum | B20: ='Sb rate sheet, HEM and Points'!B6+1% -> 0.11 | C20: Rejected Application Rate (added 1%) | E20: superannuation | I20: 43200
E21: motorbike | I21: 2400
A22: Repayment Information
A23: Monthly repayment | B23: =PMT((('Sb rate sheet, HEM and Points'!B6)/12),3*12,-E7) -> 306.53828 | C23: Calculated using 3 years as per loan guidelines as 4 years is not permissible | E23: List of liabilities (include rental commitments | I23: balance /estimated value
A24: Existing loan payments and rental obligations | B24: =I24 -> 350 | C24: As home loan will be paid out after settlement, therefore this monthly payment is not included as an ongoing obligation. Monthly rent payments are also 0 as Applicant owns the home. | E24: rent room at home | I24: 350 | J24: per month
A25: Total repayments of loans and rental obligations | B25: =SUM(B23:B24) -> 656.53828
A26: Debt Service Coverage | B26: DSC Ratio: 15.46% Benchmark Amount: $1,486.33 | C26: Policy: Since DSC is less than 35%, it is acceptable. | E26: Calculations
A27: Total Amount of all loans | B27: =E7 -> 9500 | E27: Factor | F27: Selection | G27: Score
A28: Total Tax | B28: =IF(H11<=18200,0, IF(H11<=45000,(H11-18200)*0.16, IF(H11<=135000,4288+(H11-45000)*0.3, IF(H11<=190000,31288+(H11-135000)*0.37,51638+(H11-190000)*0.45)))) -> 6076 | E28: Customer Occupation | F28: Skilled trades person | G28: =IFERROR(_xlfn.XLOOKUP(F28,'Sb rate sheet, HEM and Points'!I:I,'Sb rate sheet, HEM and Points'!J:J,,0),"") -> 90
A29: Lifestyle Assessment | B29: =F55 -> Basic | C29: Justification: The applicant is a single 30 year old with no dependents who is renting a room at home. This living situation combined with a moderate income, justifies classifying is lifestyle as Basic. | E29: Length of time in current employment | F29: 3 to 5 years | G29: =IFERROR(_xlfn.XLOOKUP(F29,'Sb rate sheet, HEM and Points'!I:I,'Sb rate sheet, HEM and Points'!J:J,,0),"") -> 40
A30: Household Expenditure Measure | B30: =B12-B28-F59 -> 12484 | C30: Based on basic lifestyle | E30: Marital Status | F30: Single | G30: =IFERROR(_xlfn.XLOOKUP(F30,'Sb rate sheet, HEM and Points'!I:I,'Sb rate sheet, HEM and Points'!J:J,,0),"") -> 20
A31: HEM borrowing limit | B31: =IF(F55="Basic",_xlfn.XLOOKUP(F56,'Sb rate sheet, HEM and Points'!A47:A57,'Sb rate sheet, HEM and Points'!C47:C57,,-1),IF(F55="Moderate",_xlfn.XLOOKUP(F56,'Sb rate sheet, HEM and Points'!A47:A57,'Sb rate sheet, HEM and Points'!E47:E57,,-1),IF(F55="Lavish",_xlfn.XLOOKUP(F56,'Sb rate sheet, HEM and Points'!A47:A57,'Sb rate sheet, HEM and Points'!G47:G57,,-1),""))) -> 170500 | C31: Round-down to $50,000 Income Tier | E31: Housing Status | F31: Renting room | G31: =IFERROR(_xlfn.XLOOKUP(F31,'Sb rate sheet, HEM and Points'!I:I,'Sb rate sheet, HEM and Points'!J:J,,0),"") -> -50
E32: Length of time at current address | F32: 2 to 4 years | G32: =_xlfn.XLOOKUP(F32,'Sb rate sheet, HEM and Points'!$I$51:$I$55,'Sb rate sheet, HEM and Points'!$J$51:$J$55,,0) -> 10
A33: Loan Officer Decision | E33: Number of Dependent Children | F33: None | G33: =IFERROR(_xlfn.XLOOKUP(F33,'Sb rate sheet, HEM and Points'!I:I,'Sb rate sheet, HEM and Points'!J:J,,0),"") -> -20
A34: Does this loan application fit within guidelines? Explain | B34: No, the requested loan term of 4 years exceeds the bank's maximum allowable term of 3 years for a motorcycle loan. Furthermore, the applicants credit score of 170 is below the minimum threshold of 324 for non-home loans. | E34: Age | F34: 26 to 49 years | G34: =IFERROR(_xlfn.XLOOKUP(F34,'Sb rate sheet, HEM and Points'!I:I,'Sb rate sheet, HEM and Points'!J:J,,0),"") -> 80
A35: Recommendation | B35: Reject Applicant should try re-applying with a shorter loan duration along with opening an account in Student bank. This can increase the approval chances. Moving to a rented apartment might also help the applicant increase their approval chances. | E35: Existing Bank Customer | F35: No | G35: =IFERROR(_xlfn.XLOOKUP(F35,'Sb rate sheet, HEM and Points'!I:I,'Sb rate sheet, HEM and Points'!J:J,,0),"") -> 0
E36: Other Banks' Credit Score | F36: No score provided | G36: =IFERROR(_xlfn.XLOOKUP(F36,'Sb rate sheet, HEM and Points'!I:I,'Sb rate sheet, HEM and Points'!J:J,,0),"") -> 0
E37: Credit score | G37: =SUM(G28:G36) -> 170
E38: Category | G38: {=_xlfn.IFS(G37>400, "Prime customer",G37>=300, "Sub-prime customer",G37<300, "Reject loan application")} -> Reject loan application
E41: Loan Parameters | G41: Criteria
E42: Deposit % | F42: =(13000-9500)/13000 -> 0.26923077 | G42: =IF(F42>20%,"Yes","Reject") -> Yes
E43: Loan Term | F43: 4 | G43: =IF(F43<=3,"Yes","Reject") -> Reject
E44: Monthly Repayment | F44: =PMT((('Sb rate sheet, HEM and Points'!B6)/12),4*12,-E7) -> 240.94454
E45: Existing loan payments and rental obligations (monthly) | F45: =I24 -> 350
E46: Total repayments of loans and rental obligations (monthly) | F46: =SUM(F44:F45) -> 590.94454
E47: Total Income | F47: =H11 -> 50960
E48: Tax | F48: =IF(H11<=18200,0, IF(H11<=45000,(H11-18200)*0.16, IF(H11<=135000,4288+(H11-45000)*0.3, IF(H11<=190000,31288+(H11-135000)*0.37,51638+(H11-190000)*0.45)))) -> 6076
E49: DSC - Debt Service Coverage | F49: =F46/(H11/12) -> 0.13915492
E50: Benchmark amount (35%) | F50: =0.35*(F47/12) -> 1486.3333 | G50: =IF(F49<35%,"Yes","No") -> Yes | H50: 1486.3333
E51: Total amount of all loans | F51: =E7 -> 9500
E52: Annual amount available for debt (HEM) | F52: =F47-F48-F59 -> 12484 | G52: =IF(F58>F51,"Yes","No") -> Yes
E55: Selected lifestyle | F55: Basic
E56: Combined gross wage income (annual) | F56: =H11 -> 50960
E58: HEM borrowing limit (from table) | F58: =IF(F55="Basic",_xlfn.XLOOKUP(F56,'Sb rate sheet, HEM and Points'!$A$47:$A$58,'Sb rate sheet, HEM and Points'!$C$47:$C$58,,-1),IF(F55="Moderate",_xlfn.XLOOKUP(F56,'Sb rate sheet, HEM and Points'!$A$47:$A$58,'Sb rate sheet, HEM and Points'!$E$47:$E$58,,-1),IF(F55="Lavish",_xlfn.XLOOKUP(F56,'Sb rate sheet, HEM and Points'!$A$47:$A$58,'Sb rate sheet, HEM and Points'!$G$47:$G$58,,-1),""))) -> 170500
E59: HEM living limit (from table) | F59: =IF(F55="Basic",_xlfn.XLOOKUP(F56,'Sb rate sheet, HEM and Points'!$A$47:$A$58,'Sb rate sheet, HEM and Points'!$B$47:$B$58,,-1),IF(F55="Moderate",_xlfn.XLOOKUP(F56,'Sb rate sheet, HEM and Points'!$A$47:$A$58,'Sb rate sheet, HEM and Points'!$D$47:$D$58,,-1),IF(F55="Lavish",_xlfn.XLOOKUP(F56,'Sb rate sheet, HEM and Points'!$A$47:$A$58,'Sb rate sheet, HEM and Points'!$F$47:$F$58,,-1),""))) -> 32400

Sheet Customer 2
A1: Loan Application | E1: Information
A2: File Number | B2: 11 | E2: Student Bank Loan application form
A3: Customer Number | B3: 2 | E3: Loan details
E4: Amount requested | F4: Loan Type | G4: Individual Or Join Cr | H4: Secured Offered | I4: For How Long | J4: Proceeds of loan to be used for
A5: Identifying Information | C5: Comments | E5: 63500 | F5: home Improvement | G5: Joint | H5: 2nd mortgage | I5: 15 | J5: Home renovation adding bathrooms
A6: Customer number and name | B6: =_xlfn.CONCAT(E7," ","-"," ", E12,) -> Kitto, James - Kitto, June | E6: Customer Name | F6: Birthdate | G6: Status | H6: No of children | I6: current home own/rent how long | K6: previous home own/rent how long
A7: Age | B7: =_xlfn.CONCAT(DATEDIF($F$7,TODAY(),"Y"),"-",DATEDIF($F$12,TODAY(),"Y")) -> 37-34 | E7: Kitto, James | F7: 32051 | G7: married | H7: 1 | I7: own | J7: 11 years | K7: rent | L7: 4 year
A8: Student Bank’s credit score | B8: =_xlfn.CONCAT(G36,"-",I36) -> 630-620 | C8: Prime-Prime | E8: Employer | F8: Position | G8: Years at employer | H8: Gross Wage | I8: Previous employer and years service | K8: Credit rating | L8: Do you bank with us (details)
A9: Other banks’ credit score | B9: =_xlfn.CONCAT(K9,"-",K14) -> good-good | E9: Anglian care | F9: Cook Aged Care | G9: 7 years | H9: 63650 | I9: 3 | J9: Field care | K9: good | L9: no
A10: Gross wage income (yearly) | B10: =H9+H14 -> 112150 | E10: Joint borrower details
A11: Dividend and rental income (yearly) | B11: 0 | E11: Customer Name | F11: Birthdate | G11: Status | H11: No of children | I11: current home own/rent how long | K11: previous home own/rent how long
A12: Total income | B12: =B10+B11 -> 112150 | E12: Kitto, June | F12: 33482 | G12: married | H12: 1 | I12: own | J12: 11 years | K12: rent | L12: 4 year
E13: Employer | F13: Position | G13: Years at employer | H13: Gross Wage | I13: Previous employer and years service | K13: Credit rating | L13: Do you bank with us (details)
A14: Loan Information | E14: Cotton On Stores | F14: Retail | G14: 11 | H14: 48500 | I14: 3 years | J14: Top Hat | K14: good | L14: no
A15: Loan amount | B15: =E5 -> 63500 | C15: Home improvement loans allowed up to 70% of home value less 1st mortgage. since LTV = 42.9%, it is allowed | E15: Statement of Financial position (your assets and Liabilities)
A16: Reason for loan | B16: =J5 -> Home renovation adding bathrooms | E16: List of assets | I16: balance /estimated value
A17: Deposit amount | B17: - | C17: Not necessary for home improvements | E17: car | I17: 36500
A18: Deposit % of purchase price | B18: - | C18: Not necessary for home improvements | E18: home | I18: 870400
A19: Loan term | B19: =I5 -> 15 | E19: bank account | I19: 23500
A20: Loan rate in % per annum | B20: ='Sb rate sheet, HEM and Points'!B15 -> 0.0525 | C20: Since the loanee will make home improvements in their primary residence | E20: superannuation | I20: 864900
E21: List of liabilities (include rental commitments | I21: balance /estimated value
A22: Repayment Information | E22: home loan | I22: 310000 | J22: $2,200 per month
A23: Monthly repayment | B23: =PMT((('Sb rate sheet, HEM and Points'!B15)/12),I5*12,-E5) -> 510.46235 | E23: credit card $24,000 limit | I23: 3680
A24: Existing loan payments and rental obligations (monthly) | B24: =2200+(2.25%*24000) -> 2740 | C24: Home loan + 2.25% of credit card limit
A25: Total repayments of loans and rental obligations (monthly) | B25: =SUM(B23:B24) -> 3250.4623 | E25: Calculations
A26: Debt Service Coverage | B26: DSC Ratio: 37.48% Benchmark Amount: $3,271.04 | C26: Since DSC is less than 35%, it is acceptable. | E26: Factor | F26: Selection (Main Applicant) | G26: Score (Main Applicant) | H26: Selection (Co-Applicant) | I26: Score (Co-Applicant)
A27: Total Amount of all loans | B27: =E5+I22+(2.25%*24000*12) -> 379980 | E27: Customer Occupation | F27: Skilled trades person | G27: =IFERROR(_xlfn.XLOOKUP(F27,'Sb rate sheet, HEM and Points'!$I:$I,'Sb rate sheet, HEM and Points'!$J:$J,,0),"") -> 90 | H27: Clerical white-collar | I27: =IFERROR(_xlfn.XLOOKUP(H27,'Sb rate sheet, HEM and Points'!$I:$I,'Sb rate sheet, HEM and Points'!$J:$J,,0),"") -> 50
A28: Total Tax | B28: =J43 -> 15221 | E28: Length of time in current employment | F28: Over 5 years | G28: =IFERROR(_xlfn.XLOOKUP(F28,'Sb rate sheet, HEM and Points'!$I:$I,'Sb rate sheet, HEM and Points'!$J:$J,,0),"") -> 70 | H28: Over 5 years | I28: =IFERROR(_xlfn.XLOOKUP(H28,'Sb rate sheet, HEM and Points'!$I:$I,'Sb rate sheet, HEM and Points'!$J:$J,,0),"") -> 70
A29: Lifestyle Assessment | B29: =F53 -> Moderate | C29: The applicants are a married couple with one child, a combined income over 100,000 and significant assets including a home valued at 870,400 and super annuation at 860,000. This profile justifies classifying their lifestyle as moderate for purpose of estimating expenses. | E29: Marital Status | F29: Married | G29: =IFERROR(_xlfn.XLOOKUP(F29,'Sb rate sheet, HEM and Points'!$I:$I,'Sb rate sheet, HEM and Points'!$J:$J,,0),"") -> 70 | H29: Married | I29: =IFERROR(_xlfn.XLOOKUP(H29,'Sb rate sheet, HEM and Points'!$I:$I,'Sb rate sheet, HEM and Points'!$J:$J,,0),"") -> 70
A30: Household Expenditure Measure | B30: =B12-B28-F57 -> 51569 | E30: Housing Status | F30: Paying mortgage on own home | G30: =IFERROR(_xlfn.XLOOKUP(F30,'Sb rate sheet, HEM and Points'!$I:$I,'Sb rate sheet, HEM and Points'!$J:$J,,0),"") -> 70 | H30: Owns home | I30: =IFERROR(_xlfn.XLOOKUP(H30,'Sb rate sheet, HEM and Points'!$I:$I,'Sb rate sheet, HEM and Points'!$J:$J,,0),"") -> 100
A31: HEM borrowing limit | B31: =F56 -> 405500 | C31: Round-down to $100,000 Income Tier | E31: Length of time at current address | F31: Over 10 years | G31: =IFERROR(_xlfn.XLOOKUP(F31,'Sb rate sheet, HEM and Points'!$I:$I,'Sb rate sheet, HEM and Points'!$J:$J,,0),"") -> 100 | H31: Over 10 years | I31: =IFERROR(_xlfn.XLOOKUP(H31,'Sb rate sheet, HEM and Points'!$I:$I,'Sb rate sheet, HEM and Points'!$J:$J,,0),"") -> 100
E32: Number of Dependent Children | F32: One to two | G32: =IFERROR(_xlfn.XLOOKUP(F32,'Sb rate sheet, HEM and Points'!$I:$I,'Sb rate sheet, HEM and Points'!$J:$J,,0),"") -> 50 | H32: One to two | I32: =IFERROR(_xlfn.XLOOKUP(H32,'Sb rate sheet, HEM and Points'!$I:$I,'Sb rate sheet, HEM and Points'!$J:$J,,0),"") -> 50
A33: Loan Officer Decision | E33: Age | F33: 26 to 49 years | G33: =IFERROR(_xlfn.XLOOKUP(F33,'Sb rate sheet, HEM and Points'!$I:$I,'Sb rate sheet, HEM and Points'!$J:$J,,0),"") -> 80 | H33: 26 to 49 years | I33: =IFERROR(_xlfn.XLOOKUP(H33,'Sb rate sheet, HEM and Points'!$I:$I,'Sb rate sheet, HEM and Points'!$J:$J,,0),"") -> 80
A34: Does this loan application fit within guidelines? Explain | B34: Yes, The applicants are prime borrowers with an excellent credit score. The loan amount is well within the allowable equity limit (299,280). The DSC ratio is compliant at 34.78%, just under 35% threshold. | E34: Existing Bank Customer | F34: No | G34: =IFERROR(_xlfn.XLOOKUP(F34,'Sb rate sheet, HEM and Points'!$I:$I,'Sb rate sheet, HEM and Points'!$J:$J,,0),"") -> 0 | H34: No | I34: =IFERROR(_xlfn.XLOOKUP(H34,'Sb rate sheet, HEM and Points'!$I:$I,'Sb rate sheet, HEM and Points'!$J:$J,,0),"") -> 0
A35: Recommendation | B35: Accept | E35: Other Banks' Credit Score | F35: Good | G35: =IFERROR(_xlfn.XLOOKUP(F35,'Sb rate sheet, HEM and Points'!$I:$I,'Sb rate sheet, HEM and Points'!$J:$J,,0),"") -> 100 | H35: Good | I35: =IFERROR(_xlfn.XLOOKUP(H35,'Sb rate sheet, HEM and Points'!$I:$I,'Sb rate sheet, HEM and Points'!$J:$J,,0),"") -> 100
E36: Credit score | G36: =SUM(G27:G35) -> 630 | I36: =SUM(I27:I35) -> 620
E37: Category | G37: {=_xlfn.IFS(G36>400, "Prime customer",G36>=300, "Sub-prime customer",G36<300, "Reject loan application")} -> Prime customer | I37: {=_xlfn.IFS(I36>400, "Prime customer",I36>=300, "Sub-prime customer",I36<300, "Reject loan application")} -> Prime customer
E40: Loan Parameters | G40: Criteria | I40: Tax Calculations
E41: Monthly Repayment | F41: =PMT((('Sb rate sheet, HEM and Points'!B15)/12),I5*12,-E5) -> 510.46235 | I41: Tax of Primary | J41: =IF(H9<=18200,0, IF(H9<=45000,(H9-18200)*0.16, IF(H9<=135000,4288+(H9-45000)*0.3, IF(H9<=190000,31288+(H9-135000)*0.37,51638+(H9-190000)*0.45)))) -> 9883
E42: Existing loan payments and rental obligations (monthly) | F42: =2200+(2.25%*24000) -> 2740 | I42: Tax of Secondary | J42: =IF(H14<=18200,0, IF(H14<=45000,(H14-18200)*0.16, IF(H14<=135000,4288+(H14-45000)*0.3, IF(H14<=190000,31288+(H14-135000)*0.37,51638+(H14-190000)*0.45)))) -> 5338
E43: Total repayments of loans and rental obligations (monthly) | F43: =SUM(F41:F42) -> 3250.4623 | I43: Total Tax | J43: =SUM(J41:J42) -> 15221
E44: Total Income | F44: =H9+H14 -> 112150
E45: Tax | F45: =J43 -> 15221
E46: DSC - Debt Service Coverage | F46: =F43/((H9+H14)/12) -> 0.34779802 | G46: =IF(F46<35%,"Yes","No") -> Yes
E47: Benchmark amount (35%) | F47: =0.35*(F44/12) -> 3271.0417
E48: Benchmark amount (40%) | F48: =0.4*(F44/12) -> 3738.3333
E49: Total amount of all loans | F49: =E5+I22+(2.25%*24000*12) -> 379980
E50: LTV - Loan-to-Value Ratio | F50: =(I22+E5)/I18 -> 0.42911305 | G50: =IF(((70%*I18)-I22)>E5,"Yes","No") -> Yes
E51: Annual amount available for debt (HEM) | F51: =F44-F45-F57 -> 51569 | G51: =IF(F56>F49,"Yes","No") -> Yes
E53: Selected lifestyle | F53: Moderate
E54: Combined gross wage income (annual) | F54: =F44 -> 112150
E56: HEM borrowing limit (from table) | F56: =IF(F53="Basic",_xlfn.XLOOKUP(F54,'Sb rate sheet, HEM and Points'!$A$47:$A$58,'Sb rate sheet, HEM and Points'!$C$47:$C$58,,-1),IF(F53="Moderate",_xlfn.XLOOKUP(F54,'Sb rate sheet, HEM and Points'!$A$47:$A$58,'Sb rate sheet, HEM and Points'!$E$47:$E$58,,-1),IF(F53="Lavish",_xlfn.XLOOKUP(F54,'Sb rate sheet, HEM and Points'!$A$47:$A$58,'Sb rate sheet, HEM and Points'!$G$47:$G$58,,-1),""))) -> 405500
E57: HEM living limit (from table) | F57: =IF(F53="Basic",_xlfn.XLOOKUP(F54,'Sb rate sheet, HEM and Points'!$A$47:$A$58,'Sb rate sheet, HEM and Points'!$B$47:$B$58,,-1),IF(F53="Moderate",_xlfn.XLOOKUP(F54,'Sb rate sheet, HEM and Points'!$A$47:$A$58,'Sb rate sheet, HEM and Points'!$D$47:$D$58,,-1),IF(F53="Lavish",_xlfn.XLOOKUP(F54,'Sb rate sheet, HEM and Points'!$A$47:$A$58,'Sb rate sheet, HEM and Points'!$F$47:$F$58,,-1),""))) -> 45360

Sheet Customer 3
A1: Loan Application | E1: Information
A2: File Number | B2: 11 | E2: Student Bank Loan application form
A3: Customer Number | B3: 3 | E3: Loan details
E4: Amount requested | F4: Loan Type | G4: Individual Or Join Cr | H4: Secured Offered | I4: For How Long | J4: Proceeds of loan to be used for
A5: Identifying Information | C5: Comments | E5: 5000 | F5: credit card | G5: Individual | H5: Unsecured | J5: new credit card
A6: Customer number and name | B6: =E7 -> Lam, Row | E6: Customer Name | F6: Birthdate | G6: Status | H6: No of children | I6: current home own/rent how long | K6: previous home own/rent how long
A7: Age | B7: =DATEDIF(DATE(2008,1,1), DATE(2025,8,1), "Y") -> 17 | E7: Lam, Row | F7: 39448 | G7: single | H7: nil | I7: at home
A8: Student Bank’s credit score | B8: 0 | C8: Reject. Since the credit score is –250, Student Bank policy assumes a minimum score of 0; hence, the score has been recorded as 0. Since Row is an apprentice, we have considered him as an unskilled labour and not a skilled labour. | E8: Employer | F8: Position | G8: Years at employer | H8: Gross Wage | I8: Previous employer and years service | K8: Credit rating | L8: Do you bank with us (details)
A9: Other banks’ credit score | B9: None | E9: Ultimo Electrical | F9: Apprentice | G9: 2 | H9: 48880 | K9: none | L9: yes
A10: Gross wage income (yearly) | B10: =H9 -> 48880 | E10: Joint borrower details
A11: Dividend and rental income (yearly) | B11: 0 | E11: Customer Name | F11: Birthdate | G11: Status | H11: No of children | I11: current home own/rent how long | K11: previous home own/rent how long
A12: Total income | B12: =B10+B11 -> 48880
E13: Employer | F13: Position | G13: Years at employer | H13: Gross Wage | I13: Previous employer and years service | K13: Credit rating | L13: Do you bank with us (details)
A14: Loan Information
A15: Loan amount | B15: =E5 -> 5000 | E15: Statement of Financial position (your assets and Liabilities)
A16: Reason for loan | B16: =J5 -> new credit card | E16: List of assets | H16: balance /estimated value
A17: Deposit amount | B17: - | C17: Not necessary for Credit Card | E17: Car | H17: 13500
A18: Deposit % of purchase price | B18: - | C18: Not necessary for Credit Card | E18: savings account | H18: 3490
A19: Loan term | B19: - | C19: Not necessary for Credit Card | E19: superannuation | H19: 12030
A20: Loan rate in % per annum | B20: ='Sb rate sheet, HEM and Points'!B27+1% -> 0.19 | C20: Rejected Interest Rate on Credit Card (added 1%)
E21: List of liabilities (include rental commitments | H21: balance /estimated value
A22: Repayment Information | E22: Loan Parents | H22: 5000 | I22: 100 per month
A23: Monthly repayment | B23: =5000*2.25% -> 112.5 | C23: In line with Student Bank policy, monthly repayments on credit cards are calculated at 2.25% of the approved credit limit (not the outstanding balance) or $25, whichever is greater. For this application, the requested limit of $5,000 results in a monthly repayment of $112.50.
A24: Existing loan payments and rental obligations | B24: =100 -> 100 | E24: Calculations
A25: Total repayments of loans and rental obligations | B25: =SUM(B23:B24) -> 212.5
A26: Debt Service Coverage | B26: DSC Ratio: 5.22% Benchmark Amount: $1,425.67 | C26: Since DSC is less than 35%, it is acceptable. | E26: Factor | F26: Selection | G26: Score
A27: Total Amount of all loans | B27: =H22+E5 -> 10000 | E27: Customer Occupation | F27: Unskilled worker | G27: =IFERROR(_xlfn.XLOOKUP(F27,'Sb rate sheet, HEM and Points'!$I:$I,'Sb rate sheet, HEM and Points'!$J:$J,,0),"") -> 30
A28: Total Tax | B28: =IF(H9<=18200,0, IF(H9<=45000,(H9-18200)*0.16, IF(H9<=135000,4288+(H9-45000)*0.3, IF(H9<=190000,31288+(H9-135000)*0.37,51638+(H9-190000)*0.45)))) -> 5452 | E28: Length of time in current employment | F28: 1 to 2 years | G28: =IFERROR(_xlfn.XLOOKUP(F28,'Sb rate sheet, HEM and Points'!$I:$I,'Sb rate sheet, HEM and Points'!$J:$J,,0),"") -> 10
A29: Lifestyle Assessment | B29: =F52 -> Basic | C29: The applicant is a 17 year old apprentice who lives at home with family and is single with no dependents. Given his age, living situation and modest income, his lifestyle is classified as Basic. | E29: Marital Status | F29: Single | G29: =IFERROR(_xlfn.XLOOKUP(F29,'Sb rate sheet, HEM and Points'!$I:$I,'Sb rate sheet, HEM and Points'!$J:$J,,0),"") -> 20
A30: Household Expenditure Measure | B30: =B12-B28-F56 -> 11028 | E30: Housing Status | F30: Lives with friends or family | G30: =IFERROR(_xlfn.XLOOKUP(F30,'Sb rate sheet, HEM and Points'!$I:$I,'Sb rate sheet, HEM and Points'!$J:$J,,0),"") -> -70
A31: HEM borrowing limit | B31: =F55 -> 60000 | C31: Round-down to $40,000 Income Tier | E31: Length of time at current address | F31: Over 10 years | G31: =_xlfn.XLOOKUP(F31,'Sb rate sheet, HEM and Points'!$I$51:$I$55,'Sb rate sheet, HEM and Points'!$J$51:$J$55,,0) -> 80
E32: Number of Dependent Children | F32: None | G32: =IFERROR(_xlfn.XLOOKUP(F32,'Sb rate sheet, HEM and Points'!$I:$I,'Sb rate sheet, HEM and Points'!$J:$J,,0),"") -> -20
A33: Loan Officer Decision | E33: Age | F33: Under 18 years | G33: =IFERROR(_xlfn.XLOOKUP(F33,'Sb rate sheet, HEM and Points'!$I:$I,'Sb rate sheet, HEM and Points'!$J:$J,,0),"") -> -400
A34: Does this loan application fit within guidelines? Explain | B34: No. The applicant is 17 years of age. Bank policy on "Non- Desirable Loans" explicitly prohibits lending to customers aged under 18 years (Section 16.8). The applicant is legally a minor and cannot enter into a credit contract. | E34: Existing Bank Customer | F34: Yes | G34: =IFERROR(_xlfn.XLOOKUP(F34,'Sb rate sheet, HEM and Points'!$I:$I,'Sb rate sheet, HEM and Points'!$J:$J,,0),"") -> 100
A35: Recommendation | B35: REJECT Row should reapply after turning 18 and may consider a joint application with Student Bank to begin building a positive credit history. | E35: Other Banks' Credit Score | F35: No score provided | G35: =IFERROR(_xlfn.XLOOKUP(F35,'Sb rate sheet, HEM and Points'!$I:$I,'Sb rate sheet, HEM and Points'!$J:$J,,0),"") -> 0
E36: Credit score | G36: =SUM(G27:G35) -> -250
E37: Category | G37: {=_xlfn.IFS(G36>400, "Prime customer",G36>=300, "Sub-prime customer",G36<300, "Reject loan application")} -> Reject loan application
E40: Loan Parameters | G40: Criteria
E41: Age | F41: 17 | G41: =IF(F41>=18,"Yes","Reject") -> Reject
E42: Monthly Repayment | F42: =5000*2.25% -> 112.5
E43: Existing loan payments and rental obligations (monthly) | F43: =100 -> 100
E44: Total repayments of loans and rental obligations (monthly) | F44: =SUM(F42:F43) -> 212.5
E45: Total Income | F45: =H9 -> 48880
E46: Tax | F46: =IF(H9<=18200,0, IF(H9<=45000,(H9-18200)*0.16, IF(H9<=135000,4288+(H9-45000)*0.3, IF(H9<=190000,31288+(H9-135000)*0.37,51638+(H9-190000)*0.45)))) -> 5452
E47: DSC - Debt Service Coverage | F47: =F44/((H9+H14)/12) -> 0.052168576 | G47: =IF(F47<35%,"Yes","No") -> Yes
E48: Benchmark amount (35%) | F48: =0.35*(F45/12) -> 1425.6667
E49: Total amount of all loans | F49: =H22+E5 -> 10000
E50: Annual amount available for debt (HEM) | F50: =F45-F46-F56 -> 11028 | G50: =IF(F52>F49,"Yes","No") -> Yes
E52: Selected lifestyle | F52: Basic
E53: Combined gross wage income (annual) | F53: =F45 -> 48880
E55: HEM borrowing limit (from table) | F55: =IF(F52="Basic",_xlfn.XLOOKUP(F53,'Sb rate sheet, HEM and Points'!$A$47:$A$58,'Sb rate sheet, HEM and Points'!$C$47:$C$58,,-1),IF(F52="Moderate",_xlfn.XLOOKUP(F53,'Sb rate sheet, HEM and Points'!$A$47:$A$58,'Sb rate sheet, HEM and Points'!$E$47:$E$58,,-1),IF(F52="Lavish",_xlfn.XLOOKUP(F53,'Sb rate sheet, HEM and Points'!$A$47:$A$58,'Sb rate sheet, HEM and Points'!$G$47:$G$58,,-1),""))) -> 60000
E56: HEM living limit (from table) | F56: =IF(F52="Basic",_xlfn.XLOOKUP(F53,'Sb rate sheet, HEM and Points'!$A$47:$A$58,'Sb rate sheet, HEM and Points'!$B$47:$B$58,,-1),IF(F52="Moderate",_xlfn.XLOOKUP(F53,'Sb rate sheet, HEM and Points'!$A$47:$A$58,'Sb rate sheet, HEM and Points'!$D$47:$D$58,,-1),IF(F52="Lavish",_xlfn.XLOOKUP(F53,'Sb rate sheet, HEM and Points'!$A$47:$A$58,'Sb rate sheet, HEM and Points'!$F$47:$F$58,,-1),""))) -> 32400

Sheet Customer 4
A1: Loan Application | E1: Information
A2: File Number | B2: 11 | E2: Student Bank Loan application form
A3: Customer Number | B3: 4 | E3: Loan details
E4: Amount requested | F4: Loan Type | G4: Individual Or Join Cr | H4: Secured Offered | I4: For How Long | J4: Proceeds of loan to be used for
A5: Identifying Information | C5: Comments | E5: 320000 | F5: home | G5: individual | H5: home | I5: 30 | J5: selling current family home and buy home unit valued at $560,000
A6: Customer number and name | B6: =E7 -> Lazarus, Se | E6: Customer Name | F6: Birthdate | G6: Status | H6: No of children | I6: current home own/rent how long | K6: previous home own/rent how long
A7: Age | B7: =DATEDIF(DATE(1990,7,1), DATE(2025,8,1), "Y") -> 35 | E7: Lazarus, Se | F7: 33055 | G7: divorced | H7: 2 | I7: own | J7: 12 years | K7: rent | L7: 5 Years
A8: Student Bank’s credit score | B8: 490 - Prime | C8: Prime | E8: Employer | F8: Position | G8: Years at employer | H8: Gross Wage | I8: Previous employer and years service | K8: Credit rating | L8: Do you bank with us (details)
A9: Other banks’ credit score | B9: None | E9: NSW Ambulance | F9: Senior officer | G9: 10 | H9: 81536 | I9: housewife | K9: na | L9: no
A10: Gross wage income (yearly) | B10: =H9 -> 81536 | E10: Joint borrower details
A11: Dividend and rental income (yearly) | B11: 0 | E11: Customer Name | F11: Birthdate | G11: Status | H11: No of children | I11: current home own/rent how long | K11: previous home own/rent how long
A12: Total income | B12: =B10+B11 -> 81536
E13: Employer | F13: Position | G13: Years at employer | H13: Gross Wage | I13: Previous employer and years service | K13: Credit rating | L13: Do you bank with us (details)
A14: Loan Information
A15: Loan amount | B15: =E5 -> 320000 | E15: Statement of Financial position (your assets and Liabilities)
A16: Reason for loan | B16: =J5 -> selling current family home and buy home unit valued at $560,000 | E16: List of assets | I16: balance /estimated value
A17: Deposit amount | B17: =560000-E5 -> 240000 | C17: From sale of half share of family home | E17: car | I17: 5780
A18: Deposit % of purchase price | B18: =F50/560000 -> 0.42857143 | C18: Deposit is 42.86% which is greater than the required 10% minimum deposit. | E18: bank accounts | I18: 34000
A19: Loan term | B19: =I5 -> 30 | E19: superannuation | I19: 327000
A20: Loan rate in % per annum | B20: ='Sb rate sheet, HEM and Points'!C31 -> 0.06 | C20: since owner occupied | E20: family home (half Share) | I20: 480000
E21: List of liabilities (include rental commitments | I21: balance /estimated value
A22: Repayment Information | E22: loan on family home (half Share) | I22: 240000 | J22: $1700 per month | K22: half share of loan repayment to be paid out on settlement
A23: Monthly repayment | B23: =PMT((('Sb rate sheet, HEM and Points'!C31)/12),I5*12,-E5) -> 1918.5617 | E23: credit card limit $16,000 | I23: 2300
A24: Existing loan payments and rental obligations | B24: =(2.25%*16000) -> 360 | C24: Justification: As home loan will be paid out after settlement, therefore this monthly payment is not included as an ongoing obligation. Monthly rent payments are also 0 as Applicant owns her home.
A25: Total repayments of loans and rental obligations | B25: =SUM(B23:B24) -> 2278.5617 | E25: Calculations
A26: Debt Service Coverage | B26: DSC Ratio: 33.53% Benchmark Amount (40%): $2,717.87 | C26: Policy: Since DSC is less than 40%, it is acceptable. The applicant's Debt Service Coverage ratio must be 40% or lower for Residential Real Estate as per policy
A27: Total Amount of all loans | B27: =E5+(2.25%*16000*12) -> 324320 | C27: Justification: Existing home loan not included as it will be paid out on settlement. | E27: Factor | F27: Selection | G27: Score
A28: Total Tax | B28: =IF(H9<=18200,0, IF(H9<=45000,(H9-18200)*0.16, IF(H9<=135000,4288+(H9-45000)*0.3, IF(H9<=190000,31288+(H9-135000)*0.37,51638+(H9-190000)*0.45)))) -> 15248.8 | E28: Customer Occupation | F28: Senior professional/business executive | G28: =IFERROR(_xlfn.XLOOKUP(F28,'Sb rate sheet, HEM and Points'!$I:$I,'Sb rate sheet, HEM and Points'!$J:$J,,0),"") -> 100
A29: Lifestyle Assessment | B29: =F56 -> Moderate | C29: Justification: The applicant is a senior officer and a single parent with two children. This profile along with an income of $80,000 is why the lifestyle has been set to moderate for the purpose of estimating expenses. | E29: Length of time in current employment | F29: Over 5 years | G29: =IFERROR(_xlfn.XLOOKUP(F29,'Sb rate sheet, HEM and Points'!$I:$I,'Sb rate sheet, HEM and Points'!$J:$J,,0),"") -> 70
A30: Household Expenditure Measure | B30: =B12-B28-F60 -> 25087.2 | E30: Marital Status | F30: Single | G30: =IFERROR(_xlfn.XLOOKUP(F30,'Sb rate sheet, HEM and Points'!$I:$I,'Sb rate sheet, HEM and Points'!$J:$J,,0),"") -> 20
A31: HEM borrowing limit | B31: =F59 -> 266900 | C31: Round-down to $80,000 Income Tier. Loan exceeds HEM cap | E31: Housing Status | F31: Paying mortgage on own home | G31: =IFERROR(_xlfn.XLOOKUP(F31,'Sb rate sheet, HEM and Points'!$I:$I,'Sb rate sheet, HEM and Points'!$J:$J,,0),"") -> 70
E32: Length of time at current address | F32: Over 10 years | G32: =IFERROR(_xlfn.XLOOKUP(F32,'Sb rate sheet, HEM and Points'!$I:$I,'Sb rate sheet, HEM and Points'!$J:$J,,0),"") -> 100
A33: Loan Officer Decision | E33: Number of Dependent Children | F33: One to two | G33: =IFERROR(_xlfn.XLOOKUP(F33,'Sb rate sheet, HEM and Points'!$I:$I,'Sb rate sheet, HEM and Points'!$J:$J,,0),"") -> 50
A34: Does this loan application fit within guidelines? Explain | B34: Yes. The deposit percentage is higher than 10% and the DSC ratio is lower than 40%, the application also fulfils the Household Expenditure Measure test | E34: Age | F34: 26 to 49 years | G34: =IFERROR(_xlfn.XLOOKUP(F34,'Sb rate sheet, HEM and Points'!$I:$I,'Sb rate sheet, HEM and Points'!$J:$J,,0),"") -> 80
A35: Recommendation | B35: Accept (Conditional) Loan is conditionally approved under the Moderate lifestyle assumption, provided the existing $240,000 home loan is cleared at settlement. The borrower should also confirm the deposit and consider reducing their credit card limit to strengthen repayment capacity. | E35: Existing Bank Customer | F35: No | G35: =IFERROR(_xlfn.XLOOKUP(F35,'Sb rate sheet, HEM and Points'!$I:$I,'Sb rate sheet, HEM and Points'!$J:$J,,0),"") -> 0
E36: Other Banks' Credit Score | F36: No score provided | G36: =IFERROR(_xlfn.XLOOKUP(F36,'Sb rate sheet, HEM and Points'!$I:$I,'Sb rate sheet, HEM and Points'!$J:$J,,0),"") -> 0
E37: Credit score | G37: =SUM(G28:G36) -> 490
E38: Category | G38: {=_xlfn.IFS(G37>400, "Prime customer",G37>=300, "Sub-prime customer",G37<300, "Reject loan application")} -> Prime customer
E41: Loan Parameters | G41: Criteria
E42: Monthly Repayment | F42: =PMT((('Sb rate sheet, HEM and Points'!C31)/12),I5*12,-E5) -> 1918.5617
E43: Existing loan payments and rental obligations (monthly) | F43: =(2.25%*16000) -> 360
E44: Total repayments of loans and rental obligations (monthly) | F44: =SUM(F42:F43) -> 2278.5617
E45: Total Income | F45: =H9 -> 81536
E46: Tax | F46: =IF(H9<=18200,0, IF(H9<=45000,(H9-18200)*0.16, IF(H9<=135000,4288+(H9-45000)*0.3, IF(H9<=190000,31288+(H9-135000)*0.37,51638+(H9-190000)*0.45)))) -> 15248.8
E47: DSC - Debt Service Coverage | F47: =F44/((H9+H14)/12) -> 0.33534562
E48: Benchmark amount (35%) | F48: =0.35*(F45/12) -> 2378.1333 | G48: =IF(F47<35%,"Yes","No") -> Yes
E49: Benchmark amount (40%) | F49: =0.4*(F45/12) -> 2717.8667 | G49: =IF(F47<35%,"Yes","No") -> Yes
E50: Deposit | F50: =560000-E5 -> 240000 | G50: =F50/560000 -> 0.42857143
E51: Total amount of all loans | F51: =E5+(2.25%*16000*12) -> 324320
E52: LTV - Loan-to-Value Ratio | F52: =E5/560000 -> 0.57142857 | G52: =IF(F52<90%,"Yes","No") -> Yes
E53: Annual amount available for debt (HEM) | F53: =F45-F46-F60 -> 25087.2 | G53: =IF(F59>F51,"Yes","Reject") -> Reject
E56: Selected lifestyle | F56: Moderate
E57: Combined gross wage income (annual) | F57: =F45 -> 81536
E59: HEM borrowing limit (from table) | F59: =IF(F56="Basic",_xlfn.XLOOKUP(F57,'Sb rate sheet, HEM and Points'!$A$47:$A$58,'Sb rate sheet, HEM and Points'!$C$47:$C$58,,-1),IF(F56="Moderate",_xlfn.XLOOKUP(F57,'Sb rate sheet, HEM and Points'!$A$47:$A$58,'Sb rate sheet, HEM and Points'!$E$47:$E$58,,-1),IF(F56="Lavish",_xlfn.XLOOKUP(F57,'Sb rate sheet, HEM and Points'!$A$47:$A$58,'Sb rate sheet, HEM and Points'!$G$47:$G$58,,-1),""))) -> 266900
E60: HEM living limit (from table) | F60: =IF(F56="Basic",_xlfn.XLOOKUP(F57,'Sb rate sheet, HEM and Points'!$A$47:$A$58,'Sb rate sheet, HEM and Points'!$B$47:$B$58,,-1),IF(F56="Moderate",_xlfn.XLOOKUP(F57,'Sb rate sheet, HEM and Points'!$A$47:$A$58,'Sb rate sheet, HEM and Points'!$D$47:$D$58,,-1),IF(F56="Lavish",_xlfn.XLOOKUP(F57,'Sb rate sheet, HEM and Points'!$A$47:$A$58,'Sb rate sheet, HEM and Points'!$F$47:$F$58,,-1),""))) -> 41200

Sheet Customer 5
A1: Loan Application | E1: Information
A2: File Number | B2: 11 | E2: Student Bank Loan application form
A3: Customer Number | B3: 5 | E3: Loan details
E4: Amount requested | F4: Loan Type | G4: Individual Or Join Cr | H4: Secured Offered | I4: For How Long | J4: Proceeds of loan to be used for
A5: Identifying Information | C5: Comments | E5: 49000 | F5: camper van | G5: Joint | H5: camper van | I5: 5 | J5: buy 2014 22ft. Daydream caravan $62,000 - deposit $13,000
A6: Customer number and name | B6: =_xlfn.CONCAT(E7," ","-"," ", E12,) -> Mariani, Chris - Mariani, Kate | E6: Customer Name | F6: Birthdate | G6: Status | H6: No of children | I6: current home own/rent how long | K6: previous home own/rent how long
A7: Age | B7: =_xlfn.CONCAT(DATEDIF($F$7,TODAY(),"Y"),"-",DATEDIF($F$12,TODAY(),"Y")) -> 56-53 | E7: Mariani, Chris | F7: 25385 | G7: married | H7: left home | I7: own | J7: 18 years | K7: own | L7: 10 years
A8: Student Bank’s credit score | B8: =_xlfn.CONCAT(G37,"-",I37) -> 650-610 | C8: Prime-Prime | E8: Employer | F8: Position | G8: Years at employer | H8: Gross Wage | I8: Previous employer and years service | K8: Credit rating | L8: Do you bank with us (details)
A9: Other banks’ credit score | B9: =_xlfn.CONCAT(F36,"-",H36) -> Good-Good | E9: Thomas transport | F9: Fleet maintenance | G9: 11 years | H9: 74930 | I9: Clark Crane | J9: 12 years | K9: good | L9: savings account
A10: Gross wage income (yearly) | B10: =H9+H14 -> 126160 | E10: Joint borrower details
A11: Dividend and rental income (yearly) | B11: 0 | E11: Customer Name | F11: Birthdate | G11: Status | H11: No of children | I11: current home own/rent how long | K11: previous home own/rent how long
A12: Total income | B12: =B10+B11 -> 126160 | E12: Mariani, Kate | F12: 26359 | G12: married | H12: left home | I12: own | J12: 18 years | K12: own | L12: 10 years
E13: Employer | F13: Position | G13: Years at employer | H13: Gross Wage | I13: Previous employer | J13: how long | K13: Credit rating | L13: Do you bank with us (details)
A14: Loan Information | E14: Sydney Bus | F14: Administrative officer | G14: 20 years | H14: 51230 | K14: good | L14: savings account
A15: Loan amount | B15: =E5 -> 49000 | E15: Statement of Financial position (your assets and Liabilities)
A16: Reason for loan | B16: =J5 -> buy 2014 22ft. Daydream caravan $62,000 - deposit $13,000 | E16: List of assets | I16: balance /estimated value
A17: Deposit amount | B17: 13000 | E17: bank account | I17: 16500
A18: Deposit % of purchase price | B18: =13000/62000 -> 0.20967742 | C18: Lower than minimum deposit : 25% | E18: superannuation | I18: 974240
A19: Loan term | B19: =I5 -> 5 | E19: cars | I19: 149500
A20: Loan rate in % per annum | B20: ='Sb rate sheet, HEM and Points'!B8 -> 0.1025 | E20: home | I20: 1346000
E21: List of liabilities (include rental commitments | I21: balance /estimated value
A22: Repayment Information | E22: car loan | I22: 54000 | J22: $1,200 per month
A23: Monthly repayment | B23: =PMT((('Sb rate sheet, HEM and Points'!B8)/12),I5*12,-E5) -> 1047.1429 | E23: Mastercard limit $25,000 | I23: 2360
A24: Existing loan payments and rental obligations | B24: =1200+(2.25%*25000) -> 1762.5
A25: Total repayments of loans and rental obligations | B25: =SUM(B23:B24) -> 2809.6429 | E25: Calculations
A26: Debt Service Coverage | B26: DSC Ratio: 26.72% Benchmark Amount: $3,679.67 | C26: Policy: Since DSC is less than 35%, it is acceptable.
A27: Total Amount of all loans | B27: =E5+I22+(2.25%*25000*12) -> 109750 | E27: Factor | F27: Selection | G27: Score | H27: Selection (Co-Applicant) | I27: Score (Co-Applicant)
A28: Total Tax | B28: =J45 -> 19424 | E28: Customer Occupation | F28: Skilled trades person | G28: =IFERROR(_xlfn.XLOOKUP(F28,'Sb rate sheet, HEM and Points'!$I:$I,'Sb rate sheet, HEM and Points'!$J:$J,,0),"") -> 90 | H28: Clerical white-collar | I28: =IFERROR(_xlfn.XLOOKUP(H28,'Sb rate sheet, HEM and Points'!$I:$I,'Sb rate sheet, HEM and Points'!$J:$J,,0),"") -> 50
A29: Lifestyle Assessment | B29: =F55 -> Lavish | C29: Justification: Given their high combined income, significant assets (including a home owned which is valued at over $1.3 million and nearly $1 million in superannuation), and substantial savings, their lifestyle is classified as "Lavish". | E29: Length of time in current employment | F29: Over 5 years | G29: =IFERROR(_xlfn.XLOOKUP(F29,'Sb rate sheet, HEM and Points'!$I:$I,'Sb rate sheet, HEM and Points'!$J:$J,,0),"") -> 70 | H29: Over 5 years | I29: =IFERROR(_xlfn.XLOOKUP(H29,'Sb rate sheet, HEM and Points'!$I:$I,'Sb rate sheet, HEM and Points'!$J:$J,,0),"") -> 70
A30: Household Expenditure Measure | B30: =B12-B28-F59 -> 38416 | E30: Marital Status | F30: Married | G30: =IFERROR(_xlfn.XLOOKUP(F30,'Sb rate sheet, HEM and Points'!$I:$I,'Sb rate sheet, HEM and Points'!$J:$J,,0),"") -> 70 | H30: Married | I30: =IFERROR(_xlfn.XLOOKUP(H30,'Sb rate sheet, HEM and Points'!$I:$I,'Sb rate sheet, HEM and Points'!$J:$J,,0),"") -> 70
A31: HEM borrowing limit | B31: =F58 -> 465600 | C31: Round-down to $125,000 Income Tier | E31: Housing Status | F31: Owns home | G31: =IFERROR(_xlfn.XLOOKUP(F31,'Sb rate sheet, HEM and Points'!$I:$I,'Sb rate sheet, HEM and Points'!$J:$J,,0),"") -> 100 | H31: Owns home | I31: =IFERROR(_xlfn.XLOOKUP(H31,'Sb rate sheet, HEM and Points'!$I:$I,'Sb rate sheet, HEM and Points'!$J:$J,,0),"") -> 100
E32: Length of time at current address | F32: Over 10 years | G32: =IFERROR(_xlfn.XLOOKUP(F32,'Sb rate sheet, HEM and Points'!$I:$I,'Sb rate sheet, HEM and Points'!$J:$J,,0),"") -> 100 | H32: Over 10 years | I32: =IFERROR(_xlfn.XLOOKUP(H32,'Sb rate sheet, HEM and Points'!$I:$I,'Sb rate sheet, HEM and Points'!$J:$J,,0),"") -> 100
A33: Loan Officer Decision | E33: Number of Dependent Children | F33: None | G33: =IFERROR(_xlfn.XLOOKUP(F33,'Sb rate sheet, HEM and Points'!$I:$I,'Sb rate sheet, HEM and Points'!$J:$J,,0),"") -> -20 | H33: None | I33: =IFERROR(_xlfn.XLOOKUP(H33,'Sb rate sheet, HEM and Points'!$I:$I,'Sb rate sheet, HEM and Points'!$J:$J,,0),"") -> -20
A34: Does this loan application fit within guidelines? Explain | B34: No, the applicants are strong contenders to get the banks approval. However the deposit of $13,000 (20.97%) falls below the bank's mandatory 25% deposit for camper van loans. The required deposit to approve the loan would be $15,500. | E34: Age | F34: 50 to 69 years | G34: =IFERROR(_xlfn.XLOOKUP(F34,'Sb rate sheet, HEM and Points'!$I:$I,'Sb rate sheet, HEM and Points'!$J:$J,,0),"") -> 40 | H34: 50 to 69 years | I34: =IFERROR(_xlfn.XLOOKUP(H34,'Sb rate sheet, HEM and Points'!$I:$I,'Sb rate sheet, HEM and Points'!$J:$J,,0),"") -> 40
A35: Recommendation | B35: Accept (Conditional) Accept if the applicant(s) can deposit 25% i.e. $15,500 | E35: Existing Bank Customer | F35: Yes | G35: =IFERROR(_xlfn.XLOOKUP(F35,'Sb rate sheet, HEM and Points'!$I:$I,'Sb rate sheet, HEM and Points'!$J:$J,,0),"") -> 100 | H35: Yes | I35: =IFERROR(_xlfn.XLOOKUP(H35,'Sb rate sheet, HEM and Points'!$I:$I,'Sb rate sheet, HEM and Points'!$J:$J,,0),"") -> 100
E36: Other Banks' Credit Score | F36: Good | G36: =IFERROR(_xlfn.XLOOKUP(F36,'Sb rate sheet, HEM and Points'!$I:$I,'Sb rate sheet, HEM and Points'!$J:$J,,0),"") -> 100 | H36: Good | I36: =IFERROR(_xlfn.XLOOKUP(H36,'Sb rate sheet, HEM and Points'!$I:$I,'Sb rate sheet, HEM and Points'!$J:$J,,0),"") -> 100
E37: Credit score | G37: =SUM(G28:G36) -> 650 | I37: =SUM(I28:I36) -> 610
E38: Category | G38: {=_xlfn.IFS(G37>400, "Prime customer",G37>=300, "Sub-prime customer",G37<300, "Reject loan application")} -> Prime customer | I38: {=_xlfn.IFS(I37>400, "Prime customer",I37>=300, "Sub-prime customer",I37<300, "Reject loan application")} -> Prime customer
E41: Loan Parameters
E42: Monthly Repayment | F42: =PMT((('Sb rate sheet, HEM and Points'!B8)/12),I5*12,-E5) -> 1047.1429 | I42: Tax Calculations
E43: Existing loan payments and rental obligations (monthly) | F43: =1200+(2.25%*25000) -> 1762.5 | I43: Tax of Primary | J43: =IF(H9<=18200,0, IF(H9<=45000,(H9-18200)*0.16, IF(H9<=135000,4288+(H9-45000)*0.3, IF(H9<=190000,31288+(H9-135000)*0.37,51638+(H9-190000)*0.45)))) -> 13267
E44: Total repayments of loans and rental obligations (monthly) | F44: =SUM(F42:F43) -> 2809.6429 | I44: Tax of Secondary | J44: =IF(H14<=18200,0,IF(H14<=45000,(H14-18200)*0.16,IF(H14<=135000,4288+(H14-45000)*0.3,IF(H14<=190000,31288+(H14-135000)*0.37,51638+(H14-190000)*0.45)))) -> 6157
E45: Total Income | F45: =H9+H14 -> 126160 | I45: Total Tax | J45: =SUM(J43:J44) -> 19424
E46: Tax | F46: =J45 -> 19424
E47: Deposit ($13,000) | F47: =13000/62000 -> 0.20967742 | G47: =IF((F47/62000)>25%,"Yes","No") -> No
E48: DSC - Debt Service Coverage | F48: =F44/(F45/12) -> 0.26724568 | G48: =IF(F48<35%,"Yes","No") -> Yes
E49: Benchmark amount (35%) | F49: =0.35*(F45/12) -> 3679.6667
E50: Total amount of all loans | F50: =E5+I22+(2.25%*25000*12) -> 109750 | G50: =IF(F51<90%,"Yes","No") -> Yes
E51: LTV - Loan-to-Value Ratio | F51: =E5/62000 -> 0.79032258 | G51: =IF(F56>F50,"Yes","No") -> Yes
E52: Annual amount available for debt (HEM) | F52: =F45-F46-F59 -> 38416
E55: Selected lifestyle | F55: Lavish
E56: Combined gross wage income (annual) | F56: =F45 -> 126160
E58: HEM borrowing limit (from table) | F58: =IF(F55="Basic",_xlfn.XLOOKUP(F56,'Sb rate sheet, HEM and Points'!$A$47:$A$58,'Sb rate sheet, HEM and Points'!$C$47:$C$58,,-1),IF(F55="Moderate",_xlfn.XLOOKUP(F56,'Sb rate sheet, HEM and Points'!$A$47:$A$58,'Sb rate sheet, HEM and Points'!$E$47:$E$58,,-1),IF(F55="Lavish",_xlfn.XLOOKUP(F56,'Sb rate sheet, HEM and Points'!$A$47:$A$58,'Sb rate sheet, HEM and Points'!$G$47:$G$58,,-1),""))) -> 465600
E59: HEM living limit (from table) | F59: =IF(F55="Basic",_xlfn.XLOOKUP(F56,'Sb rate sheet, HEM and Points'!$A$47:$A$58,'Sb rate sheet, HEM and Points'!$B$47:$B$58,,-1),IF(F55="Moderate",_xlfn.XLOOKUP(F56,'Sb rate sheet, HEM and Points'!$A$47:$A$58,'Sb rate sheet, HEM and Points'!$D$47:$D$58,,-1),IF(F55="Lavish",_xlfn.XLOOKUP(F56,'Sb rate sheet, HEM and Points'!$A$47:$A$58,'Sb rate sheet, HEM and Points'!$F$47:$F$58,,-1),""))) -> 68320

Sheet Sb rate sheet, HEM and Points
A1: Student Bank Loan minimum interest rates and maximum terms
A2: Loan Type | B2: interest rate new | C2: interest rate used | D2: max term | E2: normal repayment type | I2: Occupation | J2: Points
A3: 1. Loans for new and used vehicles/consumer mortgage
A4: Cars | B4: 0.0825 | C4: 0.095 | D4: 5yrs | E4: monthly | I4: Category | J4: Points
A5: Trucks | B5: 0.1075 | C5: 0.12 | D5: 7yrs | E5: monthly | I5: Self-employed 5y+ | J5: 70
A6: Motorcycles | B6: 0.1 | C6: 0.115 | D6: 3yrs | E6: monthly | I6: Self-employed 4-2y | J6: 30
A7: Boats | B7: 0.105 | C7: 0.1175 | D7: 4yrs | E7: monthly | I7: Self-employed <2y | J7: -50
A8: Campers | B8: 0.1025 | C8: 0.1175 | D8: 5yrs | E8: monthly | I8: Senior professional/business executive | J8: 100
I9: Clerical white-collar | J9: 50
A10: 2. Personal/household items loans | I10: Skilled trades person | J10: 90
A11: electronic items and white goods | B11: 0.1025 | C11: 0.12 | D11: 3yrs | E11: monthly | I11: Unskilled worker | J11: 30
A12: furniture and other items | B12: 0.0975 | C12: 0.11 | D12: 4yrs | E12: monthly | I12: Part time worker | J12: 10
I13: Stay-at-home partner | J13: 10
A14: 3. Home equity and home improvement loans | I14: Retired | J14: 0
A15: primary residences | B15: 0.0525 | D15: 15yrs | E15: monthly
A16: non-primary residences | B16: 0.065 | D16: 10yrs | E16: monthly
I17: Years in current employment
A18: 4. Unsecured loans | I18: Bucket | J18: Points
A19: Debt consolidation | B19: 0.12 | D19: 3yrs | E19: monthly | I19: Over 5 years | J19: 70
A20: Other | B20: 0.1 | D20: 3yrs | E20: monthly | I20: 3 to 5 years | J20: 40
I21: 1 to 2 years | J21: 10
A22: 5. Secured loans | I22: Under 1 year | J22: -50
A23: land and building security | B23: 0.055 | D23: 5yr | E23: monthly | I23: No length (retired/stay-at-home) | J23: 0
A24: other forms | B24: 0.06 | D24: 5yr | E24: monthly
A26: 6. Credit cards | I26: Marital status
A27: Classic Card | B27: 0.18 | I27: Category | J27: Points
I28: Married | J28: 70
A29: 7. Residential Real Estate Loans | C29: rate for | I29: Informal relationship | J29: 40
B30: current rate | C30: debt test | I30: Single | J30: 20
A31: owner occupied | B31: 0.04 | C31: 0.06 | D31: 30yrs | E31: monthly
A32: investment loan | B32: 0.05 | C32: 0.07 | D32: 20yrs | E32: monthly
I33: Housing status
I34: Category | J34: Points
A35: Acceptable credit scores non home loans | I35: Owns home | J35: 100
A36: Above 450 | B36: prime customer | D36: standard interest rate | I36: Paying mortgage on own home | J36: 70
A37: between 325 and 449 | B37: sub prime customer | D37: increase interest rate | I37: Renting | J37: 40
A38: below 324 | B38: reject loan application | I38: Renting room | J38: -50
I39: Lives with friends or family | J39: -70
A40: Acceptable credit scores home loans
A41: Above 400 | B41: prime customer | D41: standard interest rate
A42: between 300 and 399 | B42: sub prime customer | D42: increase interest rate | I42: Years at current address (Owns/Paying mortgage)
A43: below 299 | B43: reject loan application | I43: Bucket | J43: Points
I44: Over 10 years | J44: 100
I45: 5 to 9 years | J45: 70
A46: Household Expenditure Measure (select lifestyle in Inputs) | I46: 2 to 4 years | J46: 20
A47: Gross income | B47: Basic living | C47: Basic borrowing | D47: Moderate living | E47: Moderate borrowing | F47: Lavish living | G47: Lavish borrowing | I47: Under 2 years | J47: -20
A48: 40000 | B48: 32400 | C48: 60000
A49: 50000 | B49: 32400 | C49: 170500 | D49: 39000 | E49: 89000
A50: 60000 | B50: 32400 | C50: 230500 | D50: 39000 | E50: 137430 | I50: Years at current address (Rents/Room/Friends-Family)
A51: 70000 | B51: 32400 | C51: 300000 | D51: 40100 | E51: 200400 | I51: Bucket | J51: Points
A52: 80000 | B52: 32400 | C52: 340000 | D52: 41200 | E52: 266900 | F52: 50000 | G52: 195900 | I52: Over 10 years | J52: 80
A53: 90000 | B53: 32400 | C53: 415000 | D53: 43500 | E53: 335500 | F53: 50000 | G53: 260500 | I53: 5 to 9 years | J53: 50
A54: 100000 | B54: 32400 | C54: 485000 | D54: 45360 | E54: 405500 | F54: 58320 | G54: 327000 | I54: 2 to 4 years | J54: 10
A55: 125000 | B55: 32400 | C55: 645500 | D55: 50360 | E55: 554700 | F55: 68320 | G55: 465600 | I55: Under 2 years | J55: -40
A56: 150000 | B56: 32400 | C56: 817500 | D56: 55360 | E56: 677900 | F56: 78320 | G56: 538600
A57: 200000 | B57: 32400 | C57: 1144000 | D57: 60360 | E57: 968500 | F57: 88320 | G57: 792800
A58: 500000 | B58: 32400 | C58: 3140500 | D58: 70360 | E58: 2806967 | F58: 108320 | G58: 2472763 | I58: Number of dependent children
I59: Bucket | J59: Points
I60: None | J60: -20
I61: One to two | J61: 50
I62: Three to four | J62: 70
I63: Five or more | J63: -50
I66: Age
I67: Bucket | J67: Points
I68: Over 70 years | J68: -400
I69: 50 to 69 years | J69: 40
I70: 26 to 49 years | J70: 80
I71: 18 to 25 years | J71: 10
I72: Under 18 years | J72: -400
I75: Existing Student Bank customer
I76: Category | J76: Points
I77: Yes | J77: 100
I78: No | J78: 0
I81: Other banks’ credit score class
I82: Category | J82: Points
I83: Good | J83: 100
I84: Fair | J84: 10
I85: Slow-paying or Poor | J85: -250
I86: Debt judgement | J86: -600
I87: No score provided | J87: 0
I89: HEM
I90: Category | J90: Points
I91: Basic | J91: -
I92: Moderate | J92: -
I93: Lavish | J93: -
